{
  "list": {
    "g1": [
      {
        "id": "2022072918349",
        "event_id": "18349",
        "start_time": "2022-07-29T04:10:00+09:00",
        "end_time": "2022-07-29T04:20:00+09:00",
        "area": {
          "id": "130",
          "name": "東京"
        },
        "service": {
          "id": "g1",
          "name": "ＮＨＫ総合１",
          "logo_s": {
            "url": "//www.nhk.or.jp/common/img/media/gtv-100x50.png",
            "width": "100",
            "height": "50"
          },
          "logo_m": {
            "url": "//www.nhk.or.jp/common/img/media/gtv-200x100.png",
            "width": "200",
            "height": "100"
          },
          "logo_l": {
            "url": "//www.nhk.or.jp/common/img/media/gtv-200x200.png",
            "width": "200",
            "height": "200"
          }
        },
        "title": "時論公論　【出演】ＮＨＫ解説委員",
        "subtitle": "▽混沌（とん）とした時代、次々と押し寄せるニュースの裏に、何があるのか？“明日を生きる指針”を提供する解説番組。",
        "content": "",
        "act": "",
        "genres": [
          "0006",
          "0000",
          "0007"
        ]
      },
      {
        "id": "2022072918350",
        "event_id": "18350",
        "start_time": "2022-07-29T04:20:00+09:00",
        "end_time": "2022-07-29T05:00:00+09:00",
        "area": {
          "id": "130",
          "name": "東京"
        },
        "service": {
          "id": "g1",
          "name": "ＮＨＫ総合１",
          "logo_s": {
            "url": "//www.nhk.or.jp/common/img/media/gtv-100x50.png",
            "width": "100",
            "height": "50"
          },
          "logo_m": {
            "url": "//www.nhk.or.jp/common/img/media/gtv-200x100.png",
            "width": "200",
            "height": "100"
          },
          "logo_l": {
            "url": "//www.nhk.or.jp/common/img/media/gtv-200x200.png",
            "width": "200",
            "height": "200"
          }
        },
        "title": "国際報道２０２２　台湾有事に備え防空訓練を強化",
        "subtitle": "ウクライナ最新情勢▽台湾有事に備え現地で防空訓練を強化▽米ＧＤＰ発表▽メタバース出店の成功と失敗の分かれ目は？その戦略を追う▽その他の国際ニュース",
        "content": "台湾で２５日から年に１度の大規模軍事演習と防空訓練が行われる。軍事演習は中国による侵攻を想定し、初期に受ける攻撃への対応や重要施設の防護、制海権の確保、敵の上陸阻止などの作戦の進め方を検証する。ことしは、ウクライナ侵攻をうけて演習が強化されることになっている。有事の可能性を身近に感じ始め、備えを新たにする台湾の状況を伝える。",
        "act": "【キャスター】油井秀樹，【キャスター】角谷直也，【キャスター】中川栞",
        "genres": [
          "0005",
          "0002",
          "0006"
        ]
      },
      {
        "id": "2022072918351",
        "event_id": "18351",
        "start_time": "2022-07-29T05:00:00+09:00",
        "end_time": "2022-07-29T06:00:00+09:00",
        "area": {
          "id": "130",
          "name": "東京"
        },
        "service": {
          "id": "g1",
          "name": "ＮＨＫ総合１",
          "logo_s": {
            "url": "//www.nhk.or.jp/common/img/media/gtv-100x50.png",
            "width": "100",
            "height": "50"
          },
          "logo_m": {
            "url": "//www.nhk.or.jp/common/img/media/gtv-200x100.png",
            "width": "200",
            "height": "100"
          },
          "logo_l": {
            "url": "//www.nhk.or.jp/common/img/media/gtv-200x200.png",
            "width": "200",
            "height": "200"
          }
        },
        "title": "ＮＨＫニュース　おはよう日本",
        "subtitle": "きょうのスタート、カラフルに！国内外で起きた最新ニュースをお届け！今日一日の気象情報、スポーツもコンパクトにまとめてお伝えします。　　",
        "content": "一日の始まりはこの番組から！世界から届く国際ニュースに、きのうより一段深い国内ニュースなど、朝いちばんの最新情報をカラフルにわかりやすく、丁寧にお伝えします！今日一日はどんな天気？傘はいる？お住いの地域の予報を生映像とともに！世界のメディアが伝える驚きのニュース・スポーツ情報・ＮＨＫニュースサイトの注目記事・日本各地の話題もたっぷり！きょう一日を有意義に過ごせるお得な情報を届けます！",
        "act": "【キャスター】三條雅幸，副島萌生，八田知大，佐藤あゆみ，【気象キャスター】檜山靖洋，近藤奈央",
        "genres": [
          "0000",
          "0002",
          "0100"
        ]
      },
      {
        "id": "2022072918356",
        "event_id": "18356",
        "start_time": "2022-07-29T06:00:00+09:00",
        "end_time": "2022-07-29T06:30:00+09:00",
        "area": {
          "id": "130",
          "name": "東京"
        },
        "service": {
          "id": "g1",
          "name": "ＮＨＫ総合１",
          "logo_s": {
            "url": "//www.nhk.or.jp/common/img/media/gtv-100x50.png",
            "width": "100",
            "height": "50"
          },
          "logo_m": {
            "url": "//www.nhk.or.jp/common/img/media/gtv-200x100.png",
            "width": "200",
            "height": "100"
          },
          "logo_l": {
            "url": "//www.nhk.or.jp/common/img/media/gtv-200x200.png",
            "width": "200",
            "height": "200"
          }
        },
        "title": "ＮＨＫニュース　おはよう日本",
        "subtitle": "きょうのスタート、カラフルに！国内外の最新ニュースをお届け！気になるニュースの解説・スポーツ情報・気象中継など、役立つ情報満載でお伝えします！",
        "content": "一日の始まりはこの番組から！世界から届く国際ニュースに、きのうより一段深い国内ニュースなど、朝いちばんの最新情報をカラフルにわかりやすく、丁寧にお伝えします！ニュースの現場からの生中継！国内外のスポーツ情報もたっぷり！予報士が朝の空気とともに伝える一日の気象情報・気になるニュースの生解説も！使える・役立つ情報満載でお伝えします！",
        "act": "【キャスター】三條雅幸，伊藤海彦，副島萌生，佐藤あゆみ，【気象キャスター】檜山靖洋，近藤奈央，【スポーツキャスター】堀菜保子",
        "genres": [
          "0000",
          "0002",
          "0100"
        ]
      },
      {
        "id": "2022072918358",
        "event_id": "18358",
        "start_time": "2022-07-29T06:30:00+09:00",
        "end_time": "2022-07-29T07:00:00+09:00",
        "area": {
          "id": "130",
          "name": "東京"
        },
        "service": {
          "id": "g1",
          "name": "ＮＨＫ総合１",
          "logo_s": {
            "url": "//www.nhk.or.jp/common/img/media/gtv-100x50.png",
            "width": "100",
            "height": "50"
          },
          "logo_m": {
            "url": "//www.nhk.or.jp/common/img/media/gtv-200x100.png",
            "width": "200",
            "height": "100"
          },
          "logo_l": {
            "url": "//www.nhk.or.jp/common/img/media/gtv-200x200.png",
            "width": "200",
            "height": "200"
          }
        },
        "title": "ＮＨＫニュース　おはよう日本",
        "subtitle": "押さえておきたい経済情報「おはｂｉｚ」・世界の驚きニュース・ニュースサイトの注目記事・気象情報・役立つ情報満載です　　　　　　　　　　【キャスター】三條雅幸ほか",
        "content": "きょうのスタート、カラフルに！朝いちばんの最新情報をわかりやすく、丁寧にお伝えします！ビジネスパーソンが押さえておきたい経済情報をサクっとテンポよく！世界のメディアが伝える驚きのニュースも！今どんな天気？傘はいる？一日の気象情報を予報士が朝の空気とともに生中継！使える・役立つ情報満載でお伝えします！",
        "act": "【キャスター】三條雅幸，伊藤海彦，副島萌生，佐藤あゆみ，【気象キャスター】檜山靖洋，近藤奈央，【スポーツキャスター】堀菜保子，【おはＢｉｚキャスター】神子田章博",
        "genres": [
          "0000",
          "0002",
          "0100"
        ]
      },
      {
        "id": "2022072918361",
        "event_id": "18361",
        "start_time": "2022-07-29T07:00:00+09:00",
        "end_time": "2022-07-29T07:45:00+09:00",
        "area": {
          "id": "130",
          "name": "東京"
        },
        "service": {
          "id": "g1",
          "name": "ＮＨＫ総合１",
          "logo_s": {
            "url": "//www.nhk.or.jp/common/img/media/gtv-100x50.png",
            "width": "100",
            "height": "50"
          },
          "logo_m": {
            "url": "//www.nhk.or.jp/common/img/media/gtv-200x100.png",
            "width": "200",
            "height": "100"
          },
          "logo_l": {
            "url": "//www.nhk.or.jp/common/img/media/gtv-200x200.png",
            "width": "200",
            "height": "200"
          }
        },
        "title": "ＮＨＫニュース　おはよう日本",
        "subtitle": "きょうのスタート、カラフルに！気になる現場からの生中継やニュースの背景に切り込む特集も！地域の話題・スポーツ・詳しい気象情報など　　　　　　　　　　　　　　　　",
        "content": "一日の始まりはこの番組から！世界から届く国際ニュースに、きのうより一段深い国内ニュースなど、あさ一番の最新情報をカラフルにわかりやすく、丁寧にお伝えします！けさの天気は？傘はいる？一日の気象情報を予報士が朝の空気とともにつたえる気象中継！気になるニュースの現場からのＬｉｖｅもお届け。ニュースの背景に鋭く迫る特集に日本各地の話題も・使える・役立つ情報満載でお伝えします！",
        "act": "【キャスター】三條雅幸，伊藤海彦，副島萌生，佐藤あゆみ，【気象キャスター】檜山靖洋，近藤奈央，【スポーツキャスター】堀菜保子，【おはＢｉｚキャスター】神子田章博",
        "genres": [
          "0000",
          "0002",
          "0100"
        ]
      },
      {
        "id": "2022072918362",
        "event_id": "18362",
        "start_time": "2022-07-29T07:45:00+09:00",
        "end_time": "2022-07-29T08:00:00+09:00",
        "area": {
          "id": "130",
          "name": "東京"
        },
        "service": {
          "id": "g1",
          "name": "ＮＨＫ総合１",
          "logo_s": {
            "url": "//www.nhk.or.jp/common/img/media/gtv-100x50.png",
            "width": "100",
            "height": "50"
          },
          "logo_m": {
            "url": "//www.nhk.or.jp/common/img/media/gtv-200x100.png",
            "width": "200",
            "height": "100"
          },
          "logo_l": {
            "url": "//www.nhk.or.jp/common/img/media/gtv-200x200.png",
            "width": "200",
            "height": "200"
          }
        },
        "title": "ＮＨＫニュース　おはよう日本（関東甲信越）",
        "subtitle": "関東甲信越のニュースと交通・気象情報▽各地のいまを見つめる特集も",
        "content": "関東甲信越のニュースと交通・気象情報▽各地のいまを見つめる特集も",
        "act": "【キャスター】三條雅幸，副島萌生，【気象キャスター】檜山靖洋",
        "genres": [
          "0000",
          "0009",
          "0010"
        ]
      },
      {
        "id": "2022072918364",
        "event_id": "18364",
        "start_time": "2022-07-29T08:00:00+09:00",
        "end_time": "2022-07-29T08:15:00+09:00",
        "area": {
          "id": "130",
          "name": "東京"
        },
        "service": {
          "id": "g1",
          "name": "ＮＨＫ総合１",
          "logo_s": {
            "url": "//www.nhk.or.jp/common/img/media/gtv-100x50.png",
            "width": "100",
            "height": "50"
          },
          "logo_m": {
            "url": "//www.nhk.or.jp/common/img/media/gtv-200x100.png",
            "width": "200",
            "height": "100"
          },
          "logo_l": {
            "url": "//www.nhk.or.jp/common/img/media/gtv-200x200.png",
            "width": "200",
            "height": "200"
          }
        },
        "title": "【連続テレビ小説】ちむどんどん（８０）「御三味（うさんみ）に愛をこめて」",
        "subtitle": "暢子は和彦の母・重子に、おいしいお弁当を作っていく作戦を続けていた。そして和彦は重子に手紙で思いを伝える。沖縄では良子が夫・石川の家族に、再び向かい合う決心を…",
        "content": "暢子（黒島結菜）は和彦（宮沢氷魚）の母・重子に、美味（おい）しいお弁当を作って持っていく作戦を続けていた。そして和彦は手紙で重子に思いを伝えて…。沖縄では良子（川口春奈）が暢子の苦労に刺激を受けて。自分のことをなかなか認めてくれない夫・石川（山田裕貴）の家族に、再び向かい合う決心をする。そんな良子の姿に石川も心を固めて、実家に乗り込むことに…。",
        "act": "【作】羽原大介，【出演】黒島結菜，鈴木保奈美，竜星涼，川口春奈，中原丈雄，【語り】ジョン・カビラ，【音楽】岡部啓一，高田龍一，帆足圭吾",
        "genres": [
          "0300"
        ]
      },
      {
        "id": "2022072918365",
        "event_id": "18365",
        "start_time": "2022-07-29T08:15:00+09:00",
        "end_time": "2022-07-29T09:55:00+09:00",
        "area": {
          "id": "130",
          "name": "東京"
        },
        "service": {
          "id": "g1",
          "name": "ＮＨＫ総合１",
          "logo_s": {
            "url": "//www.nhk.or.jp/common/img/media/gtv-100x50.png",
            "width": "100",
            "height": "50"
          },
          "logo_m": {
            "url": "//www.nhk.or.jp/common/img/media/gtv-200x100.png",
            "width": "200",
            "height": "100"
          },
          "logo_l": {
            "url": "//www.nhk.or.jp/common/img/media/gtv-200x200.png",
            "width": "200",
            "height": "200"
          }
        },
        "title": "あさイチ「プレミアムトーク　江口のりこ」",
        "subtitle": "▽プレミアムトーク　江口のりこ",
        "content": "▽プレミアムトーク　江口のりこさん▽華丸大吉との生トークをお楽しみに！▽特選！エンタ　イチオシ映画▽グリーンスタイル　水草を楽しむ！アクアリウムを始めよう【キャスター】博多華丸・大吉、鈴木奈穂子",
        "act": "【ゲスト】江口のりこ，【講師】水草職人…早坂誠，【キャスター】博多華丸，博多大吉，鈴木奈穂子，【リポーター】駒村多恵",
        "genres": [
          "0202",
          "0203",
          "0800"
        ]
      },
      {
        "id": "2022072918370",
        "event_id": "18370",
        "start_time": "2022-07-29T09:55:00+09:00",
        "end_time": "2022-07-29T10:00:00+09:00",
        "area": {
          "id": "130",
          "name": "東京"
        },
        "service": {
          "id": "g1",
          "name": "ＮＨＫ総合１",
          "logo_s": {
            "url": "//www.nhk.or.jp/common/img/media/gtv-100x50.png",
            "width": "100",
            "height": "50"
          },
          "logo_m": {
            "url": "//www.nhk.or.jp/common/img/media/gtv-200x100.png",
            "width": "200",
            "height": "100"
          },
          "logo_l": {
            "url": "//www.nhk.or.jp/common/img/media/gtv-200x200.png",
            "width": "200",
            "height": "200"
          }
        },
        "title": "みんなの体操",
        "subtitle": "多胡肇、吉江晴菜、今井菜津美、杉井勇介",
        "content": "【出演】多胡肇，吉江晴菜，今井菜津美，杉井勇介",
        "act": "【出演】多胡肇，吉江晴菜，今井菜津美，杉井勇介",
        "genres": [
          "0115",
          "1015",
          "0203"
        ]
      },
      {
        "id": "2022072918371",
        "event_id": "18371",
        "start_time": "2022-07-29T10:00:00+09:00",
        "end_time": "2022-07-29T10:05:00+09:00",
        "area": {
          "id": "130",
          "name": "東京"
        },
        "service": {
          "id": "g1",
          "name": "ＮＨＫ総合１",
          "logo_s": {
            "url": "//www.nhk.or.jp/common/img/media/gtv-100x50.png",
            "width": "100",
            "height": "50"
          },
          "logo_m": {
            "url": "//www.nhk.or.jp/common/img/media/gtv-200x100.png",
            "width": "200",
            "height": "100"
          },
          "logo_l": {
            "url": "//www.nhk.or.jp/common/img/media/gtv-200x200.png",
            "width": "200",
            "height": "200"
          }
        },
        "title": "ニュース・気象情報",
        "subtitle": "",
        "content": "",
        "act": "",
        "genres": [
          "0000",
          "0001"
        ]
      },
      {
        "id": "2022072918372",
        "event_id": "18372",
        "start_time": "2022-07-29T10:05:00+09:00",
        "end_time": "2022-07-29T10:55:00+09:00",
        "area": {
          "id": "130",
          "name": "東京"
        },
        "service": {
          "id": "g1",
          "name": "ＮＨＫ総合１",
          "logo_s": {
            "url": "//www.nhk.or.jp/common/img/media/gtv-100x50.png",
            "width": "100",
            "height": "50"
          },
          "logo_m": {
            "url": "//www.nhk.or.jp/common/img/media/gtv-200x100.png",
            "width": "200",
            "height": "100"
          },
          "logo_l": {
            "url": "//www.nhk.or.jp/common/img/media/gtv-200x200.png",
            "width": "200",
            "height": "200"
          }
        },
        "title": "キャッチ！世界のトップニュース",
        "subtitle": "ロシアによるウクライナ侵攻。現地の最新情勢や各国の動きなど、世界のテレビ局が放送したニュースからピックアップしてお伝えします。",
        "content": "▽各国の放送局が伝える注目ニュースをピックアップ　▽焦点や背景を分かりやすく解説　▽特集ワールド・アイズ　※内容変更の場合あり　【キャスター】小林雄，高橋彩",
        "act": "【キャスター】小林雄，高橋彩",
        "genres": [
          "0005",
          "0006",
          "0200"
        ]
      },
      {
        "id": "2022072918375",
        "event_id": "18375",
        "start_time": "2022-07-29T10:55:00+09:00",
        "end_time": "2022-07-29T11:00:00+09:00",
        "area": {
          "id": "130",
          "name": "東京"
        },
        "service": {
          "id": "g1",
          "name": "ＮＨＫ総合１",
          "logo_s": {
            "url": "//www.nhk.or.jp/common/img/media/gtv-100x50.png",
            "width": "100",
            "height": "50"
          },
          "logo_m": {
            "url": "//www.nhk.or.jp/common/img/media/gtv-200x100.png",
            "width": "200",
            "height": "100"
          },
          "logo_l": {
            "url": "//www.nhk.or.jp/common/img/media/gtv-200x200.png",
            "width": "200",
            "height": "200"
          }
        },
        "title": "みんなのうた「あなたがどこかで」",
        "subtitle": "「あなたがどこかで」うた：安全地帯",
        "content": "「あなたがどこかで」うた：安全地帯",
        "act": "",
        "genres": [
          "0409",
          "0504"
        ]
      },
      {
        "id": "2022072918376",
        "event_id": "18376",
        "start_time": "2022-07-29T11:00:00+09:00",
        "end_time": "2022-07-29T11:05:00+09:00",
        "area": {
          "id": "130",
          "name": "東京"
        },
        "service": {
          "id": "g1",
          "name": "ＮＨＫ総合１",
          "logo_s": {
            "url": "//www.nhk.or.jp/common/img/media/gtv-100x50.png",
            "width": "100",
            "height": "50"
          },
          "logo_m": {
            "url": "//www.nhk.or.jp/common/img/media/gtv-200x100.png",
            "width": "200",
            "height": "100"
          },
          "logo_l": {
            "url": "//www.nhk.or.jp/common/img/media/gtv-200x200.png",
            "width": "200",
            "height": "200"
          }
        },
        "title": "ニュース・気象情報",
        "subtitle": "",
        "content": "",
        "act": "",
        "genres": [
          "0000",
          "0001"
        ]
      },
      {
        "id": "2022072918377",
        "event_id": "18377",
        "start_time": "2022-07-29T11:05:00+09:00",
        "end_time": "2022-07-29T11:30:00+09:00",
        "area": {
          "id": "130",
          "name": "東京"
        },
        "service": {
          "id": "g1",
          "name": "ＮＨＫ総合１",
          "logo_s": {
            "url": "//www.nhk.or.jp/common/img/media/gtv-100x50.png",
            "width": "100",
            "height": "50"
          },
          "logo_m": {
            "url": "//www.nhk.or.jp/common/img/media/gtv-200x100.png",
            "width": "200",
            "height": "100"
          },
          "logo_l": {
            "url": "//www.nhk.or.jp/common/img/media/gtv-200x200.png",
            "width": "200",
            "height": "200"
          }
        },
        "title": "探検ファクトリー「優しい座り心地と進化のヒミツ　理容・美容イス」",
        "subtitle": "漫才コンビ・中川家がモノ作りの現場を“探検”。ヘアサロン用の電動椅子を作る工場で、リクライニング機能など最新技術に驚きの連続！共演者はすっちー（吉本新喜劇座長）",
        "content": "漫才コンビ・中川家と、吉本新喜劇の人気キャラ・すち子が魅力溢（あふ）れる町工場を“探検”する番組。「日本のもの作りの底力」「働く人の情熱」に迫る。今回は、ヘアサロンで愛用される理容・美容椅子を手掛ける大阪の工場へ。国内のみならず、世界１２０か国で使用中ともいわれる大人気の理容・美容椅子だ。人気の秘密は、座るお客さんの快適性はもちろん、理容師・美容師の使い勝手も徹底的に追求した商品づくりにあった。",
        "act": "【出演】中川家，すっちー",
        "genres": [
          "0505",
          "0800"
        ]
      },
      {
        "id": "2022072918379",
        "event_id": "18379",
        "start_time": "2022-07-29T11:30:00+09:00",
        "end_time": "2022-07-29T11:54:00+09:00",
        "area": {
          "id": "130",
          "name": "東京"
        },
        "service": {
          "id": "g1",
          "name": "ＮＨＫ総合１",
          "logo_s": {
            "url": "//www.nhk.or.jp/common/img/media/gtv-100x50.png",
            "width": "100",
            "height": "50"
          },
          "logo_m": {
            "url": "//www.nhk.or.jp/common/img/media/gtv-200x100.png",
            "width": "200",
            "height": "100"
          },
          "logo_l": {
            "url": "//www.nhk.or.jp/common/img/media/gtv-200x200.png",
            "width": "200",
            "height": "200"
          }
        },
        "title": "ひるまえほっと",
        "subtitle": "▽いま旬市場▽かんたんごはん",
        "content": "グルメ！旅！防災！トレンド！くらしをより豊かに楽しくするカラフルな企画、そして関東甲信越の知られざる魅力や話題をお届けします！ほっとなひとときをあなたに…。",
        "act": "【キャスター】古谷敏郎",
        "genres": [
          "0009",
          "0202",
          "0205"
        ]
      },
      {
        "id": "2022072918384",
        "event_id": "18384",
        "start_time": "2022-07-29T11:54:00+09:00",
        "end_time": "2022-07-29T12:00:00+09:00",
        "area": {
          "id": "130",
          "name": "東京"
        },
        "service": {
          "id": "g1",
          "name": "ＮＨＫ総合１",
          "logo_s": {
            "url": "//www.nhk.or.jp/common/img/media/gtv-100x50.png",
            "width": "100",
            "height": "50"
          },
          "logo_m": {
            "url": "//www.nhk.or.jp/common/img/media/gtv-200x100.png",
            "width": "200",
            "height": "100"
          },
          "logo_l": {
            "url": "//www.nhk.or.jp/common/img/media/gtv-200x200.png",
            "width": "200",
            "height": "200"
          }
        },
        "title": "気象情報",
        "subtitle": "",
        "content": "",
        "act": "",
        "genres": [
          "0001"
        ]
      },
      {
        "id": "2022072918386",
        "event_id": "18386",
        "start_time": "2022-07-29T12:00:00+09:00",
        "end_time": "2022-07-29T12:15:00+09:00",
        "area": {
          "id": "130",
          "name": "東京"
        },
        "service": {
          "id": "g1",
          "name": "ＮＨＫ総合１",
          "logo_s": {
            "url": "//www.nhk.or.jp/common/img/media/gtv-100x50.png",
            "width": "100",
            "height": "50"
          },
          "logo_m": {
            "url": "//www.nhk.or.jp/common/img/media/gtv-200x100.png",
            "width": "200",
            "height": "100"
          },
          "logo_l": {
            "url": "//www.nhk.or.jp/common/img/media/gtv-200x200.png",
            "width": "200",
            "height": "200"
          }
        },
        "title": "ニュース",
        "subtitle": "【キャスター】中山果奈",
        "content": "",
        "act": "【キャスター】中山果奈",
        "genres": [
          "0000"
        ]
      },
      {
        "id": "2022072918387",
        "event_id": "18387",
        "start_time": "2022-07-29T12:15:00+09:00",
        "end_time": "2022-07-29T12:20:00+09:00",
        "area": {
          "id": "130",
          "name": "東京"
        },
        "service": {
          "id": "g1",
          "name": "ＮＨＫ総合１",
          "logo_s": {
            "url": "//www.nhk.or.jp/common/img/media/gtv-100x50.png",
            "width": "100",
            "height": "50"
          },
          "logo_m": {
            "url": "//www.nhk.or.jp/common/img/media/gtv-200x100.png",
            "width": "200",
            "height": "100"
          },
          "logo_l": {
            "url": "//www.nhk.or.jp/common/img/media/gtv-200x200.png",
            "width": "200",
            "height": "200"
          }
        },
        "title": "ニュース（関東）",
        "subtitle": "",
        "content": "",
        "act": "",
        "genres": [
          "0000"
        ]
      },
      {
        "id": "2022072918388",
        "event_id": "18388",
        "start_time": "2022-07-29T12:20:00+09:00",
        "end_time": "2022-07-29T12:43:00+09:00",
        "area": {
          "id": "130",
          "name": "東京"
        },
        "service": {
          "id": "g1",
          "name": "ＮＨＫ総合１",
          "logo_s": {
            "url": "//www.nhk.or.jp/common/img/media/gtv-100x50.png",
            "width": "100",
            "height": "50"
          },
          "logo_m": {
            "url": "//www.nhk.or.jp/common/img/media/gtv-200x100.png",
            "width": "200",
            "height": "100"
          },
          "logo_l": {
            "url": "//www.nhk.or.jp/common/img/media/gtv-200x200.png",
            "width": "200",
            "height": "200"
          }
        },
        "title": "きょうの料理　タサン志麻の小さな台所「夏のお助けごはん」",
        "subtitle": "タサン志麻さんが、料理をもっと気楽に楽しむコツを伝授してくれるシリーズ。２回目のテーマは、「夏のお助けごはん」。志麻さん自身が夏によく作るレシピを教わります！",
        "content": "「暑くて疲れやすい夏は、料理はなるべく一品で済ませるようにしている」という志麻さん。たっぷりの野菜と刺身用のまぐろのさくを使ったボリューム感満点の「サラダニーソワーズ」や、天板ごと食卓に出せ、マリネ液で味を変えられる「オーブンでバーベキュー」をご紹介します。さらに、子どもと作ると楽しい、手軽な「チョコレートのティラミス」や、冷たい前菜におすすめの「桃とトマトのスープ」もおすすめですよ！",
        "act": "【講師】タサン志麻，【語り】浜野謙太",
        "genres": [
          "0205",
          "1015"
        ]
      },
      {
        "id": "2022072918389",
        "event_id": "18389",
        "start_time": "2022-07-29T12:43:00+09:00",
        "end_time": "2022-07-29T12:45:00+09:00",
        "area": {
          "id": "130",
          "name": "東京"
        },
        "service": {
          "id": "g1",
          "name": "ＮＨＫ総合１",
          "logo_s": {
            "url": "//www.nhk.or.jp/common/img/media/gtv-100x50.png",
            "width": "100",
            "height": "50"
          },
          "logo_m": {
            "url": "//www.nhk.or.jp/common/img/media/gtv-200x100.png",
            "width": "200",
            "height": "100"
          },
          "logo_l": {
            "url": "//www.nhk.or.jp/common/img/media/gtv-200x200.png",
            "width": "200",
            "height": "200"
          }
        },
        "title": "熱中症から命を守れ　医師からの４つのお願い",
        "subtitle": "この夏、危険度が増している熱中症。特に「高齢者」や「屋内」はリスクが高いとされる。救急の専門医に聞いた熱中症対策のポイントを４つ、短くまとめてお伝えする。",
        "content": "この夏、危険度が増している熱中症。特に「高齢者」や「屋内」はリスクが高いとされる。熱中症対策のポイントを４つ、短くまとめてお伝えする。水分補給のポイントは「のどが渇く前に」「こまめに」。起床後、入浴の前後などタイミングを決めて習慣化すると飲み忘れを防げる。屋外を歩くときは手に冷たいペットボトルをもつと効率的に体温を下げられる。救急の専門医が勧める具体的なノウハウを紹介する",
        "act": "【出演】帝京大学医学部救急科教授…三宅康史",
        "genres": [
          "0200"
        ]
      },
      {
        "id": "2022072918392",
        "event_id": "18392",
        "start_time": "2022-07-29T12:45:00+09:00",
        "end_time": "2022-07-29T13:00:00+09:00",
        "area": {
          "id": "130",
          "name": "東京"
        },
        "service": {
          "id": "g1",
          "name": "ＮＨＫ総合１",
          "logo_s": {
            "url": "//www.nhk.or.jp/common/img/media/gtv-100x50.png",
            "width": "100",
            "height": "50"
          },
          "logo_m": {
            "url": "//www.nhk.or.jp/common/img/media/gtv-200x100.png",
            "width": "200",
            "height": "100"
          },
          "logo_l": {
            "url": "//www.nhk.or.jp/common/img/media/gtv-200x200.png",
            "width": "200",
            "height": "200"
          }
        },
        "title": "【連続テレビ小説】ちむどんどん（８０）「御三味（うさんみ）に愛をこめて」",
        "subtitle": "暢子は和彦の母・重子に、おいしいお弁当を作っていく作戦を続けていた。そして和彦は重子に手紙で思いを伝える。沖縄では良子が夫・石川の家族に、再び向かい合う決心を…",
        "content": "暢子（黒島結菜）は和彦（宮沢氷魚）の母・重子に、美味（おい）しいお弁当を作って持っていく作戦を続けていた。そして和彦は手紙で重子に思いを伝えて…。沖縄では良子（川口春奈）が暢子の苦労に刺激を受けて。自分のことをなかなか認めてくれない夫・石川（山田裕貴）の家族に、再び向かい合う決心をする。そんな良子の姿に石川も心を固めて、実家に乗り込むことに…。",
        "act": "【作】羽原大介，【出演】黒島結菜，鈴木保奈美，竜星涼，川口春奈，中原丈雄，【語り】ジョン・カビラ，【音楽】岡部啓一，高田龍一，帆足圭吾",
        "genres": [
          "0300"
        ]
      },
      {
        "id": "2022072918393",
        "event_id": "18393",
        "start_time": "2022-07-29T13:00:00+09:00",
        "end_time": "2022-07-29T13:05:00+09:00",
        "area": {
          "id": "130",
          "name": "東京"
        },
        "service": {
          "id": "g1",
          "name": "ＮＨＫ総合１",
          "logo_s": {
            "url": "//www.nhk.or.jp/common/img/media/gtv-100x50.png",
            "width": "100",
            "height": "50"
          },
          "logo_m": {
            "url": "//www.nhk.or.jp/common/img/media/gtv-200x100.png",
            "width": "200",
            "height": "100"
          },
          "logo_l": {
            "url": "//www.nhk.or.jp/common/img/media/gtv-200x200.png",
            "width": "200",
            "height": "200"
          }
        },
        "title": "ニュース",
        "subtitle": "",
        "content": "",
        "act": "",
        "genres": [
          "0000"
        ]
      },
      {
        "id": "2022072918394",
        "event_id": "18394",
        "start_time": "2022-07-29T13:05:00+09:00",
        "end_time": "2022-07-29T13:55:00+09:00",
        "area": {
          "id": "130",
          "name": "東京"
        },
        "service": {
          "id": "g1",
          "name": "ＮＨＫ総合１",
          "logo_s": {
            "url": "//www.nhk.or.jp/common/img/media/gtv-100x50.png",
            "width": "100",
            "height": "50"
          },
          "logo_m": {
            "url": "//www.nhk.or.jp/common/img/media/gtv-200x100.png",
            "width": "200",
            "height": "100"
          },
          "logo_l": {
            "url": "//www.nhk.or.jp/common/img/media/gtv-200x200.png",
            "width": "200",
            "height": "200"
          }
        },
        "title": "列島ニュース",
        "subtitle": "日本列島の今が見える！ＮＨＫが地域向けに放送しているお昼のニュースを選（え）りすぐって大阪から全国に発信。地域の課題や郷土の話題を盛りだくさんでお届けします。",
        "content": "「列島各地の地域ニュースを選りすぐって大阪から全国に発信します」。全国に５４あるＮＨＫの各放送局が取材して地域向けに放送したお昼のニュースから地域の課題、地元ならではの話題などを集めて盛りだくさんでお伝えします。今年度は中継で結んで現地の放送局から伝える「列島ニュースアップ」と「ＮＨＫ　ＮＥＷＳ　ＷＥＢ」に掲載された特集記事を紹介するコーナーを新たに開始！ライブ感とネット連携を強化してお届けします",
        "act": "【キャスター】武田真一，伊藤雄彦，二宮直輝，牛田茉友，一柳亜矢子，【気象予報士】坂下恵理",
        "genres": [
          "0000"
        ]
      },
      {
        "id": "2022072918395",
        "event_id": "18395",
        "start_time": "2022-07-29T13:55:00+09:00",
        "end_time": "2022-07-29T14:00:00+09:00",
        "area": {
          "id": "130",
          "name": "東京"
        },
        "service": {
          "id": "g1",
          "name": "ＮＨＫ総合１",
          "logo_s": {
            "url": "//www.nhk.or.jp/common/img/media/gtv-100x50.png",
            "width": "100",
            "height": "50"
          },
          "logo_m": {
            "url": "//www.nhk.or.jp/common/img/media/gtv-200x100.png",
            "width": "200",
            "height": "100"
          },
          "logo_l": {
            "url": "//www.nhk.or.jp/common/img/media/gtv-200x200.png",
            "width": "200",
            "height": "200"
          }
        },
        "title": "テレビ体操",
        "subtitle": "岡本美佳、幅しげみ、今井菜津美、戸塚寛子、石川裕平",
        "content": "【出演】岡本美佳，今井菜津美，戸塚寛子，石川裕平，【ピアノ】幅しげみ",
        "act": "【出演】岡本美佳，今井菜津美，戸塚寛子，石川裕平，【ピアノ】幅しげみ",
        "genres": [
          "0115",
          "1015",
          "0203"
        ]
      },
      {
        "id": "2022072918396",
        "event_id": "18396",
        "start_time": "2022-07-29T14:00:00+09:00",
        "end_time": "2022-07-29T14:05:00+09:00",
        "area": {
          "id": "130",
          "name": "東京"
        },
        "service": {
          "id": "g1",
          "name": "ＮＨＫ総合１",
          "logo_s": {
            "url": "//www.nhk.or.jp/common/img/media/gtv-100x50.png",
            "width": "100",
            "height": "50"
          },
          "logo_m": {
            "url": "//www.nhk.or.jp/common/img/media/gtv-200x100.png",
            "width": "200",
            "height": "100"
          },
          "logo_l": {
            "url": "//www.nhk.or.jp/common/img/media/gtv-200x200.png",
            "width": "200",
            "height": "200"
          }
        },
        "title": "ニュース・気象情報",
        "subtitle": "",
        "content": "",
        "act": "",
        "genres": [
          "0000",
          "0001"
        ]
      },
      {
        "id": "2022072918397",
        "event_id": "18397",
        "start_time": "2022-07-29T14:05:00+09:00",
        "end_time": "2022-07-29T14:50:00+09:00",
        "area": {
          "id": "130",
          "name": "東京"
        },
        "service": {
          "id": "g1",
          "name": "ＮＨＫ総合１",
          "logo_s": {
            "url": "//www.nhk.or.jp/common/img/media/gtv-100x50.png",
            "width": "100",
            "height": "50"
          },
          "logo_m": {
            "url": "//www.nhk.or.jp/common/img/media/gtv-200x100.png",
            "width": "200",
            "height": "100"
          },
          "logo_l": {
            "url": "//www.nhk.or.jp/common/img/media/gtv-200x200.png",
            "width": "200",
            "height": "200"
          }
        },
        "title": "京コトはじめ「怨霊・鬼・妖怪　京都の異界」",
        "subtitle": "異界とは日常の外の世界のこと。京都では、桓武天皇の平安京遷都以来、平安京の外を、怨霊や妖怪などが現れる異界の地とみなした歴史がある。京都の異界についてひもとく。",
        "content": "異界とは、日常生活の外の世界のこと。京都では、桓武天皇が早良親王の怨霊をおそれ、平安京に遷都して以来、都の外を、怨霊や鬼、妖怪などが現れる異界の地とみなすようになる。それらがもたらす災いを防ぐため、鬼門を重視して神社仏閣を配置したり、陰陽師の呪術に頼るなどしてきた歴史がある。また、あの世に渡った先祖の霊を迎えるお盆の行事なども現在に至るまで続いてきた。京都の人にとっての異界がどんなものかひもとく。",
        "act": "【司会】森田洋平，【ゲスト】狂言師…茂山逸平，国際日本文化研究センター名誉教授…小松和彦",
        "genres": [
          "0801"
        ]
      },
      {
        "id": "2022072918398",
        "event_id": "18398",
        "start_time": "2022-07-29T14:50:00+09:00",
        "end_time": "2022-07-29T15:00:00+09:00",
        "area": {
          "id": "130",
          "name": "東京"
        },
        "service": {
          "id": "g1",
          "name": "ＮＨＫ総合１",
          "logo_s": {
            "url": "//www.nhk.or.jp/common/img/media/gtv-100x50.png",
            "width": "100",
            "height": "50"
          },
          "logo_m": {
            "url": "//www.nhk.or.jp/common/img/media/gtv-200x100.png",
            "width": "200",
            "height": "100"
          },
          "logo_l": {
            "url": "//www.nhk.or.jp/common/img/media/gtv-200x200.png",
            "width": "200",
            "height": "200"
          }
        },
        "title": "みみより！くらし解説　【出演】岩渕梢キャスター　ＮＨＫ解説委員",
        "subtitle": "▽あなたのくらしに、みみより解説！いま気になるニュースをわかりやすく、裏にはこんな深いコトが…！くらしに密着した耳よりな情報をお届けします！",
        "content": "",
        "act": "【キャスター】岩渕梢",
        "genres": [
          "0006",
          "0202",
          "0203"
        ]
      },
      {
        "id": "2022072918399",
        "event_id": "18399",
        "start_time": "2022-07-29T15:00:00+09:00",
        "end_time": "2022-07-29T15:07:00+09:00",
        "area": {
          "id": "130",
          "name": "東京"
        },
        "service": {
          "id": "g1",
          "name": "ＮＨＫ総合１",
          "logo_s": {
            "url": "//www.nhk.or.jp/common/img/media/gtv-100x50.png",
            "width": "100",
            "height": "50"
          },
          "logo_m": {
            "url": "//www.nhk.or.jp/common/img/media/gtv-200x100.png",
            "width": "200",
            "height": "100"
          },
          "logo_l": {
            "url": "//www.nhk.or.jp/common/img/media/gtv-200x200.png",
            "width": "200",
            "height": "200"
          }
        },
        "title": "ニュース・気象情報",
        "subtitle": "",
        "content": "",
        "act": "",
        "genres": [
          "0000",
          "0001"
        ]
      },
      {
        "id": "2022072918400",
        "event_id": "18400",
        "start_time": "2022-07-29T15:07:00+09:00",
        "end_time": "2022-07-29T15:10:00+09:00",
        "area": {
          "id": "130",
          "name": "東京"
        },
        "service": {
          "id": "g1",
          "name": "ＮＨＫ総合１",
          "logo_s": {
            "url": "//www.nhk.or.jp/common/img/media/gtv-100x50.png",
            "width": "100",
            "height": "50"
          },
          "logo_m": {
            "url": "//www.nhk.or.jp/common/img/media/gtv-200x100.png",
            "width": "200",
            "height": "100"
          },
          "logo_l": {
            "url": "//www.nhk.or.jp/common/img/media/gtv-200x200.png",
            "width": "200",
            "height": "200"
          }
        },
        "title": "ニュース（関東甲信越）",
        "subtitle": "",
        "content": "",
        "act": "",
        "genres": [
          "0009"
        ]
      },
      {
        "id": "2022072918401",
        "event_id": "18401",
        "start_time": "2022-07-29T15:10:00+09:00",
        "end_time": "2022-07-29T15:55:00+09:00",
        "area": {
          "id": "130",
          "name": "東京"
        },
        "service": {
          "id": "g1",
          "name": "ＮＨＫ総合１",
          "logo_s": {
            "url": "//www.nhk.or.jp/common/img/media/gtv-100x50.png",
            "width": "100",
            "height": "50"
          },
          "logo_m": {
            "url": "//www.nhk.or.jp/common/img/media/gtv-200x100.png",
            "width": "200",
            "height": "100"
          },
          "logo_l": {
            "url": "//www.nhk.or.jp/common/img/media/gtv-200x200.png",
            "width": "200",
            "height": "200"
          }
        },
        "title": "歴史探偵「岡本太郎と太陽の塔」",
        "subtitle": "１９７０年の大阪万博で誕生した岡本太郎の代表作「太陽の塔」の謎を徹底調査！太郎の業務日誌、構想スケッチなどから、誕生の秘密、形の謎、永久保存が決まった理由に迫る",
        "content": "巨大芸術作品「太陽の塔」。１９７０年の大阪万博で芸術家・岡本太郎によって誕生した。実はこの塔、太郎が勝手につくったものだった！？テレビ初公開！太郎の業務日誌から見えてきた塔誕生の影のキーパーソンとは！？近年、発見された１２０枚の太郎自筆の太陽の塔構想スケッチ。あの独特な形に込めた太郎のメッセージに迫る。太郎も同意、太陽の塔は壊されるはずだった！規則を覆して永久保存となった理由とは！？",
        "act": "【出演】佐藤二朗",
        "genres": [
          "0801"
        ]
      },
      {
        "id": "2022072918403",
        "event_id": "18403",
        "start_time": "2022-07-29T15:55:00+09:00",
        "end_time": "2022-07-29T16:00:00+09:00",
        "area": {
          "id": "130",
          "name": "東京"
        },
        "service": {
          "id": "g1",
          "name": "ＮＨＫ総合１",
          "logo_s": {
            "url": "//www.nhk.or.jp/common/img/media/gtv-100x50.png",
            "width": "100",
            "height": "50"
          },
          "logo_m": {
            "url": "//www.nhk.or.jp/common/img/media/gtv-200x100.png",
            "width": "200",
            "height": "100"
          },
          "logo_l": {
            "url": "//www.nhk.or.jp/common/img/media/gtv-200x200.png",
            "width": "200",
            "height": "200"
          }
        },
        "title": "みんなのうた「あのね　～青色の傘～」／「象だゾウ」",
        "subtitle": "「あのね　～青色の傘～」うた：Ｒｉｅ＆Ｑｏｏｎｉｅ／「象だゾウ」うた：ささきいさお",
        "content": "「あのね　～青色の傘～」うた：Ｒｉｅ＆Ｑｏｏｎｉｅ／「象だゾウ」うた：ささきいさお",
        "act": "",
        "genres": [
          "0409",
          "0504"
        ]
      },
      {
        "id": "2022072918404",
        "event_id": "18404",
        "start_time": "2022-07-29T16:00:00+09:00",
        "end_time": "2022-07-29T16:05:00+09:00",
        "area": {
          "id": "130",
          "name": "東京"
        },
        "service": {
          "id": "g1",
          "name": "ＮＨＫ総合１",
          "logo_s": {
            "url": "//www.nhk.or.jp/common/img/media/gtv-100x50.png",
            "width": "100",
            "height": "50"
          },
          "logo_m": {
            "url": "//www.nhk.or.jp/common/img/media/gtv-200x100.png",
            "width": "200",
            "height": "100"
          },
          "logo_l": {
            "url": "//www.nhk.or.jp/common/img/media/gtv-200x200.png",
            "width": "200",
            "height": "200"
          }
        },
        "title": "ニュース・気象情報",
        "subtitle": "",
        "content": "",
        "act": "",
        "genres": [
          "0000"
        ]
      },
      {
        "id": "2022072922115",
        "event_id": "22115",
        "start_time": "2022-07-29T16:05:00+09:00",
        "end_time": "2022-07-29T16:30:00+09:00",
        "area": {
          "id": "130",
          "name": "東京"
        },
        "service": {
          "id": "g1",
          "name": "ＮＨＫ総合１",
          "logo_s": {
            "url": "//www.nhk.or.jp/common/img/media/gtv-100x50.png",
            "width": "100",
            "height": "50"
          },
          "logo_m": {
            "url": "//www.nhk.or.jp/common/img/media/gtv-200x100.png",
            "width": "200",
            "height": "100"
          },
          "logo_l": {
            "url": "//www.nhk.or.jp/common/img/media/gtv-200x200.png",
            "width": "200",
            "height": "200"
          }
        },
        "title": "レイチェルのおいしい旅レシピ",
        "subtitle": "",
        "content": "",
        "act": "",
        "genres": [
          "0205",
          "0506"
        ]
      },
      {
        "id": "2022072918406",
        "event_id": "18406",
        "start_time": "2022-07-29T16:30:00+09:00",
        "end_time": "2022-07-29T17:00:00+09:00",
        "area": {
          "id": "130",
          "name": "東京"
        },
        "service": {
          "id": "g1",
          "name": "ＮＨＫ総合１",
          "logo_s": {
            "url": "//www.nhk.or.jp/common/img/media/gtv-100x50.png",
            "width": "100",
            "height": "50"
          },
          "logo_m": {
            "url": "//www.nhk.or.jp/common/img/media/gtv-200x100.png",
            "width": "200",
            "height": "100"
          },
          "logo_l": {
            "url": "//www.nhk.or.jp/common/img/media/gtv-200x200.png",
            "width": "200",
            "height": "200"
          }
        },
        "title": "セレクション",
        "subtitle": "",
        "content": "",
        "act": "",
        "genres": []
      },
      {
        "id": "2022072918407",
        "event_id": "18407",
        "start_time": "2022-07-29T17:00:00+09:00",
        "end_time": "2022-07-29T18:00:00+09:00",
        "area": {
          "id": "130",
          "name": "東京"
        },
        "service": {
          "id": "g1",
          "name": "ＮＨＫ総合１",
          "logo_s": {
            "url": "//www.nhk.or.jp/common/img/media/gtv-100x50.png",
            "width": "100",
            "height": "50"
          },
          "logo_m": {
            "url": "//www.nhk.or.jp/common/img/media/gtv-200x100.png",
            "width": "200",
            "height": "100"
          },
          "logo_l": {
            "url": "//www.nhk.or.jp/common/img/media/gtv-200x200.png",
            "width": "200",
            "height": "200"
          }
        },
        "title": "ニュース　きん５時",
        "subtitle": "大阪から全国へ届けるニュース情報番組！知られざる社会問題や話題を掘り起こして徹底取材。あなたの「知りたい」に答えます！【キャスター】武田真一・石橋亜紗",
        "content": "大阪から全国へ届けるニュース情報番組！知られざる社会問題や話題を掘り起こして徹底取材。ニュースの裏側にある物語や人間模様に迫ります。大切にしているのが、地方からの視点。気になる現場から新たな情報を見つけ、あなたの「知りたい」に答えます！　【キャスター】武田真一，石橋亜紗",
        "act": "【キャスター】武田真一，石橋亜紗",
        "genres": [
          "0000"
        ]
      },
      {
        "id": "2022072918409",
        "event_id": "18409",
        "start_time": "2022-07-29T18:00:00+09:00",
        "end_time": "2022-07-29T18:10:00+09:00",
        "area": {
          "id": "130",
          "name": "東京"
        },
        "service": {
          "id": "g1",
          "name": "ＮＨＫ総合１",
          "logo_s": {
            "url": "//www.nhk.or.jp/common/img/media/gtv-100x50.png",
            "width": "100",
            "height": "50"
          },
          "logo_m": {
            "url": "//www.nhk.or.jp/common/img/media/gtv-200x100.png",
            "width": "200",
            "height": "100"
          },
          "logo_l": {
            "url": "//www.nhk.or.jp/common/img/media/gtv-200x200.png",
            "width": "200",
            "height": "200"
          }
        },
        "title": "首都圏ネットワーク",
        "subtitle": "首都圏ネットワークがワイドになりました！「明日につながる、あなたとつながる」６０分間。いまチェックすべき首都圏最新情報は？ネットトレンドと連動してより深く！",
        "content": "番組の開始は、１９９７年４月。「首都圏ネットワーク」が今年大きく生まれ変わります。メーンキャスターに井上裕貴アナウンサーと上原光紀アナウンサーが登場。首都圏に暮らす皆さまの興味と関心に寄り添い、あなたの明日が少しでも明るく良くなりますように…。「明日につながる、あなたとつながる」。あなたに響くニュース番組でありたい。【首都圏ナビはこちら】ｗｗｗ．ｎｈｋ．ｏｒ．ｊｐ／ｓｈｕｔｏｋｅｎ／",
        "act": "【キャスター】井上裕貴，上原光紀，【フィールドリポーター】原大策，【ナビゲーター】大橋拓",
        "genres": [
          "0000",
          "0009",
          "0202"
        ]
      },
      {
        "id": "2022072918411",
        "event_id": "18411",
        "start_time": "2022-07-29T18:10:00+09:00",
        "end_time": "2022-07-29T18:30:00+09:00",
        "area": {
          "id": "130",
          "name": "東京"
        },
        "service": {
          "id": "g1",
          "name": "ＮＨＫ総合１",
          "logo_s": {
            "url": "//www.nhk.or.jp/common/img/media/gtv-100x50.png",
            "width": "100",
            "height": "50"
          },
          "logo_m": {
            "url": "//www.nhk.or.jp/common/img/media/gtv-200x100.png",
            "width": "200",
            "height": "100"
          },
          "logo_l": {
            "url": "//www.nhk.or.jp/common/img/media/gtv-200x200.png",
            "width": "200",
            "height": "200"
          }
        },
        "title": "首都圏ネットワーク",
        "subtitle": "首都圏ネットワークがワイドに！「明日につながる、あなたとつながる」６０分。気忙しい首都圏生活で役立つ情報満載。暮らしのヒントが見つかる地域密着ニュース番組です。",
        "content": "番組の開始は、１９９７年４月。「首都圏ネットワーク」が大きく生まれ変わります。メーンキャスターに井上裕貴アナウンサーと上原光紀アナウンサーが登場。「明日につながる、あなたとつながる」。日本の集積地・首都圏の目まぐるしい毎日…。そんなあなたの明日が少しでも明るく良くなりますように。あなたに響くニュース番組でありたい。【首都圏ナビはこちら】ｗｗｗ．ｎｈｋ．ｏｒ．ｊｐ／ｓｈｕｔｏｋｅｎ／",
        "act": "【キャスター】井上裕貴，上原光紀，【フィールドリポーター】原大策，【気象キャスター】船木正人",
        "genres": [
          "0000",
          "0009",
          "0202"
        ]
      },
      {
        "id": "2022072918413",
        "event_id": "18413",
        "start_time": "2022-07-29T18:30:00+09:00",
        "end_time": "2022-07-29T19:00:00+09:00",
        "area": {
          "id": "130",
          "name": "東京"
        },
        "service": {
          "id": "g1",
          "name": "ＮＨＫ総合１",
          "logo_s": {
            "url": "//www.nhk.or.jp/common/img/media/gtv-100x50.png",
            "width": "100",
            "height": "50"
          },
          "logo_m": {
            "url": "//www.nhk.or.jp/common/img/media/gtv-200x100.png",
            "width": "200",
            "height": "100"
          },
          "logo_l": {
            "url": "//www.nhk.or.jp/common/img/media/gtv-200x200.png",
            "width": "200",
            "height": "200"
          }
        },
        "title": "首都圏ネットワーク（東京・神奈川・千葉・埼玉）",
        "subtitle": "首都圏ネットワークがワイドに！「明日につながる、あなたとつながる」６０分。あなたの街のニュースや話題をきめ細かく。おかえり天気は中継も交えて詳しくお伝えします。",
        "content": "番組の開始から２５年。「首都圏ネットワーク」が生まれ変わります。目まぐるしい毎日…。「夕飯どうしよう」「コロナうんざり…」「頑張ってるのに、誰もわかってくれない」「今度、この街行ってみよう」…。そんなあなたの明日が少しでも明るく良くなりますように。どこかの誰かのニュースではない、あなたに響くニュース番組でありたい。【首都圏ナビはこちら】ｗｗｗ．ｎｈｋ．ｏｒ．ｊｐ／ｓｈｕｔｏｋｅｎ／",
        "act": "【キャスター】井上裕貴，上原光紀，【フィールドリポーター】原大策，【気象キャスター】船木正人，【気象リポーター】市村紗弥香",
        "genres": [
          "0000",
          "0009",
          "0202"
        ]
      },
      {
        "id": "2022072918416",
        "event_id": "18416",
        "start_time": "2022-07-29T19:00:00+09:00",
        "end_time": "2022-07-29T19:30:00+09:00",
        "area": {
          "id": "130",
          "name": "東京"
        },
        "service": {
          "id": "g1",
          "name": "ＮＨＫ総合１",
          "logo_s": {
            "url": "//www.nhk.or.jp/common/img/media/gtv-100x50.png",
            "width": "100",
            "height": "50"
          },
          "logo_m": {
            "url": "//www.nhk.or.jp/common/img/media/gtv-200x100.png",
            "width": "200",
            "height": "100"
          },
          "logo_l": {
            "url": "//www.nhk.or.jp/common/img/media/gtv-200x200.png",
            "width": "200",
            "height": "200"
          }
        },
        "title": "ＮＨＫニュース７",
        "subtitle": "「確かなニュース、いつでも　どこでも」　きょうの日本、世界の今　一歩先へ、一歩深く　テレビでもスマホでも　このニュースを届けたい　　　",
        "content": "「確かなニュース、いつでも　どこでも」　きょうの日本、世界の今　一歩先へ、一歩深く　テレビでもスマホでも　このニュースを届けたい",
        "act": "【キャスター】瀧川剛史，林田理沙，今井翔馬，【気象キャスター】晴山紋音",
        "genres": [
          "0000",
          "0001",
          "0100"
        ]
      },
      {
        "id": "2022072924590",
        "event_id": "24590",
        "start_time": "2022-07-29T19:30:00+09:00",
        "end_time": "2022-07-29T19:57:00+09:00",
        "area": {
          "id": "130",
          "name": "東京"
        },
        "service": {
          "id": "g1",
          "name": "ＮＨＫ総合１",
          "logo_s": {
            "url": "//www.nhk.or.jp/common/img/media/gtv-100x50.png",
            "width": "100",
            "height": "50"
          },
          "logo_m": {
            "url": "//www.nhk.or.jp/common/img/media/gtv-200x100.png",
            "width": "200",
            "height": "100"
          },
          "logo_l": {
            "url": "//www.nhk.or.jp/common/img/media/gtv-200x200.png",
            "width": "200",
            "height": "200"
          }
        },
        "title": "首都圏情報　ネタドリ！",
        "subtitle": "",
        "content": "",
        "act": "【キャスター】合原明子",
        "genres": [
          "0009",
          "0202",
          "0800"
        ]
      },
      {
        "id": "2022072918418",
        "event_id": "18418",
        "start_time": "2022-07-29T19:57:00+09:00",
        "end_time": "2022-07-29T20:42:00+09:00",
        "area": {
          "id": "130",
          "name": "東京"
        },
        "service": {
          "id": "g1",
          "name": "ＮＨＫ総合１",
          "logo_s": {
            "url": "//www.nhk.or.jp/common/img/media/gtv-100x50.png",
            "width": "100",
            "height": "50"
          },
          "logo_m": {
            "url": "//www.nhk.or.jp/common/img/media/gtv-200x100.png",
            "width": "200",
            "height": "100"
          },
          "logo_l": {
            "url": "//www.nhk.or.jp/common/img/media/gtv-200x200.png",
            "width": "200",
            "height": "200"
          }
        },
        "title": "チコちゃんに叱られる！▽カラスの漢字▽１口目のビール▽親と過ごせる時間",
        "subtitle": "今回のチコちゃんの疑問は…カラスの漢字はなぜ鳥より線が１本少ない？ビールの１口目がおいしいのはなぜ？親とあとどれくらい一緒に過ごせる？みなさんわかりますか？",
        "content": "カラスの漢字は「鳥」よりも線が１本少ない。一体なぜ１本少ないの？あつーいときに飲むビールの１口目は最高！という人は多い。ではなぜ１口目のビールはおいしいの？いつまでも元気でいると思いがちな両親。ではあとどのくらい一緒にいられるのか、その残り時間を知っていますか？今回のゲストはＡ．Ｂ．Ｃ－Ｚの河合郁人と森三中の村上知子。ふみきゅんお得意のモノマネ披露。じわっと笑える投稿動画集も必見！",
        "act": "【出演】岡村隆史，【ゲスト】村上知子，河合郁人，【リポーター】塚原愛，【声】木村祐一，【語り】森田美由紀",
        "genres": [
          "0515"
        ]
      },
      {
        "id": "2022072918419",
        "event_id": "18419",
        "start_time": "2022-07-29T20:42:00+09:00",
        "end_time": "2022-07-29T20:45:00+09:00",
        "area": {
          "id": "130",
          "name": "東京"
        },
        "service": {
          "id": "g1",
          "name": "ＮＨＫ総合１",
          "logo_s": {
            "url": "//www.nhk.or.jp/common/img/media/gtv-100x50.png",
            "width": "100",
            "height": "50"
          },
          "logo_m": {
            "url": "//www.nhk.or.jp/common/img/media/gtv-200x100.png",
            "width": "200",
            "height": "100"
          },
          "logo_l": {
            "url": "//www.nhk.or.jp/common/img/media/gtv-200x200.png",
            "width": "200",
            "height": "200"
          }
        },
        "title": "＃ＮＨＫ　番組のお知らせ",
        "subtitle": "【キャスター】片山千恵子",
        "content": "",
        "act": "【キャスター】片山千恵子",
        "genres": [
          "0207"
        ]
      },
      {
        "id": "2022072918420",
        "event_id": "18420",
        "start_time": "2022-07-29T20:45:00+09:00",
        "end_time": "2022-07-29T21:00:00+09:00",
        "area": {
          "id": "130",
          "name": "東京"
        },
        "service": {
          "id": "g1",
          "name": "ＮＨＫ総合１",
          "logo_s": {
            "url": "//www.nhk.or.jp/common/img/media/gtv-100x50.png",
            "width": "100",
            "height": "50"
          },
          "logo_m": {
            "url": "//www.nhk.or.jp/common/img/media/gtv-200x100.png",
            "width": "200",
            "height": "100"
          },
          "logo_l": {
            "url": "//www.nhk.or.jp/common/img/media/gtv-200x200.png",
            "width": "200",
            "height": "200"
          }
        },
        "title": "首都圏ニュース８４５",
        "subtitle": "「首都圏ニュース８４５」ほっと一息の時間。これさえ見れば、きょう１日の首都圏のニュース、あすの気象情報がわかる。“ちょうどいい１５分間”明日の暮らしのヒントに！",
        "content": "なにかと気忙しい首都圏生活の夜、明日に役立つ情報が満載です！。ニュースと気象情報をコンパクトにお伝えする１５分間です。あなたの街のニュースや地域の話題をきめ細かくお伝えします。各地のいまを見つめるリポートも。あなたの暮らしのヒントが見つかる、地域密着型ニュース番組です。【首都圏に暮らす人たちのニュースとくらし情報「首都圏ナビ」はこちら】ｈｔｔｐｓ：／／ｗｗｗ．ｎｈｋ．ｏｒ．ｊｐ／ｓｈｕｔｏｋｅｎ／",
        "act": "【キャスター】上原光紀，【気象キャスター】船木正人",
        "genres": [
          "0009",
          "0001",
          "0202"
        ]
      },
      {
        "id": "2022072918421",
        "event_id": "18421",
        "start_time": "2022-07-29T21:00:00+09:00",
        "end_time": "2022-07-29T22:00:00+09:00",
        "area": {
          "id": "130",
          "name": "東京"
        },
        "service": {
          "id": "g1",
          "name": "ＮＨＫ総合１",
          "logo_s": {
            "url": "//www.nhk.or.jp/common/img/media/gtv-100x50.png",
            "width": "100",
            "height": "50"
          },
          "logo_m": {
            "url": "//www.nhk.or.jp/common/img/media/gtv-200x100.png",
            "width": "200",
            "height": "100"
          },
          "logo_l": {
            "url": "//www.nhk.or.jp/common/img/media/gtv-200x200.png",
            "width": "200",
            "height": "200"
          }
        },
        "title": "ニュースウオッチ９",
        "subtitle": "▽ニュースも、角度を変えると発見がある▽夜９時・日本の、世界のニュースを詳しく▽さらに深く知りたいテーマは特集で掘り下げます▽スポーツは速報で！▽気象情報　ほか",
        "content": "▽ニュースも、角度を変えると発見がある▽夜９時・日本の、世界のニュースを詳しく▽田中、青井、山内、３人のキャスターが最新情報を届けます▽リポーターが現場に直行！▽さらに深く知りたいテーマは特集で掘り下げ▽スポーツは結果を速報で！注目のポイントも▽あすの天気をわかりやすく斉田キャスターの気象情報　ほか",
        "act": "【キャスター】田中正良，青井実，山内泉，【気象キャスター】斉田季実治",
        "genres": [
          "0000",
          "0001",
          "0100"
        ]
      },
      {
        "id": "2022072918422",
        "event_id": "18422",
        "start_time": "2022-07-29T22:00:00+09:00",
        "end_time": "2022-07-29T22:30:00+09:00",
        "area": {
          "id": "130",
          "name": "東京"
        },
        "service": {
          "id": "g1",
          "name": "ＮＨＫ総合１",
          "logo_s": {
            "url": "//www.nhk.or.jp/common/img/media/gtv-100x50.png",
            "width": "100",
            "height": "50"
          },
          "logo_m": {
            "url": "//www.nhk.or.jp/common/img/media/gtv-200x100.png",
            "width": "200",
            "height": "100"
          },
          "logo_l": {
            "url": "//www.nhk.or.jp/common/img/media/gtv-200x200.png",
            "width": "200",
            "height": "200"
          }
        },
        "title": "あの日、偶然そこにいて（３）",
        "subtitle": "歴史的瞬間や時代を象徴する「あの日」の映像。そこに映り込んだ人々をわずかな手がかりから徹底取材で探し出す。あの日からどんな人生を歩んだのか？【語り】小芝風花",
        "content": "今回のテーマは「竹の子族」と「山一證券の破綻」。ＮＨＫアーカイブスから、当時の竹の子族リーダーの引退式の映像を発見。探し出すと意外な人生が待っていた！「山一破綻」では、破綻後の支社に潜入したドキュメンタリー映像をもとに、敏腕営業課長のその後を追跡。さらに入社してわずか１年、新入社員なのに解雇されてしまった人物の映像を発見。その後を追跡すると…　当時の思いを胸に秘め、驚きの人生を送っていた！",
        "act": "【語り】小芝風花",
        "genres": [
          "0800",
          "0801",
          "0807"
        ]
      },
      {
        "id": "2022072922248",
        "event_id": "22248",
        "start_time": "2022-07-29T22:30:00+09:00",
        "end_time": "2022-07-29T22:45:00+09:00",
        "area": {
          "id": "130",
          "name": "東京"
        },
        "service": {
          "id": "g1",
          "name": "ＮＨＫ総合１",
          "logo_s": {
            "url": "//www.nhk.or.jp/common/img/media/gtv-100x50.png",
            "width": "100",
            "height": "50"
          },
          "logo_m": {
            "url": "//www.nhk.or.jp/common/img/media/gtv-200x100.png",
            "width": "200",
            "height": "100"
          },
          "logo_l": {
            "url": "//www.nhk.or.jp/common/img/media/gtv-200x200.png",
            "width": "200",
            "height": "200"
          }
        },
        "title": "街角ピアノ「渋谷　ｖｏｌ．３」",
        "subtitle": "東京・渋谷、駅ビルの４階広場に置かれたピアノ。「コロナ禍を音楽で乗り越えよう」と２０２１年１０月、設置。どんな思いでピアノを弾くのか。ノーナレーションで見つめる",
        "content": "大規模な再開発が進む東京・渋谷。１日３００万人が行き交う駅ビルの４階、京王井の頭線改札近くの広場に１台のピアノが置かれている。通勤、通学、買い物などに訪れた老若男女が通りすがりに弾いていく。金融関係の仕事をする男性、鉄道マニアの男子高校生、学校帰りの大学生、８０年の代ポップスを弾く女性、物流倉庫に勤める初老の男性、ウクライナ国歌を奏でる女性ピアニスト…大都会でさまざまな人々が心のメロディーを奏でる",
        "act": "",
        "genres": [
          "0815",
          "0415",
          "1002"
        ]
      },
      {
        "id": "2022072918424",
        "event_id": "18424",
        "start_time": "2022-07-29T22:45:00+09:00",
        "end_time": "2022-07-29T23:15:00+09:00",
        "area": {
          "id": "130",
          "name": "東京"
        },
        "service": {
          "id": "g1",
          "name": "ＮＨＫ総合１",
          "logo_s": {
            "url": "//www.nhk.or.jp/common/img/media/gtv-100x50.png",
            "width": "100",
            "height": "50"
          },
          "logo_m": {
            "url": "//www.nhk.or.jp/common/img/media/gtv-200x100.png",
            "width": "200",
            "height": "100"
          },
          "logo_l": {
            "url": "//www.nhk.or.jp/common/img/media/gtv-200x200.png",
            "width": "200",
            "height": "200"
          }
        },
        "title": "ドキュメント７２時間「東京・渋谷　眠らないレンタルスタジオで」",
        "subtitle": "渋谷駅近くのビルにあるレンタルスタジオ。４０以上の個室が早朝から深夜まで借りられる。ダンスや格闘技、美容講座など、どんな人たちが何を求めて来るんだろう。",
        "content": "ダンスや格闘技、美容講座。渋谷駅近くのビルにあるレンタルスタジオ。４０以上の個室が早朝から深夜まで借りられ、多くの人がやってくる。利用の多いダンスだけでもサルサにヒップポップ、ベリーダンスといろいろ。自主練というダンス部の高校生や、夜通し練習する若手プロダンサー。同じ趣味を持つ仲間と出会え、コロナ禍も充実していたと語る人も。大都会の片隅、眠らないレンタルスタジオに３日間、カメラを据える。",
        "act": "【語り】市川実日子",
        "genres": [
          "0800",
          "0801",
          "0202"
        ]
      },
      {
        "id": "2022072918426",
        "event_id": "18426",
        "start_time": "2022-07-29T23:15:00+09:00",
        "end_time": "2022-07-29T23:30:00+09:00",
        "area": {
          "id": "130",
          "name": "東京"
        },
        "service": {
          "id": "g1",
          "name": "ＮＨＫ総合１",
          "logo_s": {
            "url": "//www.nhk.or.jp/common/img/media/gtv-100x50.png",
            "width": "100",
            "height": "50"
          },
          "logo_m": {
            "url": "//www.nhk.or.jp/common/img/media/gtv-200x100.png",
            "width": "200",
            "height": "100"
          },
          "logo_l": {
            "url": "//www.nhk.or.jp/common/img/media/gtv-200x200.png",
            "width": "200",
            "height": "200"
          }
        },
        "title": "漫画家イエナガの複雑社会を超定義「スタジアム超進化論を超速解説の巻」",
        "subtitle": "驚異のエンタメ！スタジアム超進化論を俳優・町田啓太が超速解説！地域に変革をもたらすアイデア＆ハートフルな物語！わずか１５分で難しいことを漫画やＣＧで楽しく学ぶ",
        "content": "今日も漫画家イエナガ（町田啓太）が編集者（橋本マナミ）へ新作を売り込む。漫画のテーマは「スタジアム進化論」。ショッピング？農業体験？ＢＢＱ？地域を盛り上げるユニークアイデアが続々！スタジアムの本場アメリカで革命を起こした若き女性の奇想天外な発想とは？さらにスポーツ界のレジェンド・上原浩治さんと中村憲剛さんがスタジアムの魅力を熱弁。地域を活気づけ、絆も深めるスタジアム超進化論を超速プレゼン！",
        "act": "【出演】町田啓太，橋本マナミ",
        "genres": [
          "0800"
        ]
      },
      {
        "id": "2022072918427",
        "event_id": "18427",
        "start_time": "2022-07-29T23:30:00+09:00",
        "end_time": "2022-07-29T23:35:00+09:00",
        "area": {
          "id": "130",
          "name": "東京"
        },
        "service": {
          "id": "g1",
          "name": "ＮＨＫ総合１",
          "logo_s": {
            "url": "//www.nhk.or.jp/common/img/media/gtv-100x50.png",
            "width": "100",
            "height": "50"
          },
          "logo_m": {
            "url": "//www.nhk.or.jp/common/img/media/gtv-200x100.png",
            "width": "200",
            "height": "100"
          },
          "logo_l": {
            "url": "//www.nhk.or.jp/common/img/media/gtv-200x200.png",
            "width": "200",
            "height": "200"
          }
        },
        "title": "ニュース・気象情報",
        "subtitle": "",
        "content": "",
        "act": "",
        "genres": [
          "0000"
        ]
      },
      {
        "id": "2022072918428",
        "event_id": "18428",
        "start_time": "2022-07-29T23:35:00+09:00",
        "end_time": "2022-07-29T23:45:00+09:00",
        "area": {
          "id": "130",
          "name": "東京"
        },
        "service": {
          "id": "g1",
          "name": "ＮＨＫ総合１",
          "logo_s": {
            "url": "//www.nhk.or.jp/common/img/media/gtv-100x50.png",
            "width": "100",
            "height": "50"
          },
          "logo_m": {
            "url": "//www.nhk.or.jp/common/img/media/gtv-200x100.png",
            "width": "200",
            "height": "100"
          },
          "logo_l": {
            "url": "//www.nhk.or.jp/common/img/media/gtv-200x200.png",
            "width": "200",
            "height": "200"
          }
        },
        "title": "時論公論　【出演】ＮＨＫ解説委員",
        "subtitle": "▽混沌（とん）とした時代、次々と押し寄せるニュースの裏に、何があるのか？“明日を生きる指針”を提供する解説番組。",
        "content": "",
        "act": "",
        "genres": [
          "0006",
          "0000",
          "0007"
        ]
      },
      {
        "id": "2022072923047",
        "event_id": "23047",
        "start_time": "2022-07-29T23:45:00+09:00",
        "end_time": "2022-07-30T00:25:00+09:00",
        "area": {
          "id": "130",
          "name": "東京"
        },
        "service": {
          "id": "g1",
          "name": "ＮＨＫ総合１",
          "logo_s": {
            "url": "//www.nhk.or.jp/common/img/media/gtv-100x50.png",
            "width": "100",
            "height": "50"
          },
          "logo_m": {
            "url": "//www.nhk.or.jp/common/img/media/gtv-200x100.png",
            "width": "200",
            "height": "100"
          },
          "logo_l": {
            "url": "//www.nhk.or.jp/common/img/media/gtv-200x200.png",
            "width": "200",
            "height": "200"
          }
        },
        "title": "国際報道２０２２　原発回帰に打って出た韓国",
        "subtitle": "▽ウクライナ最新情勢▽原発回帰に打って出た韓国の背景と課題をたっぷりと▽タイの奇祭ピーターコーン、伝統の仮面づくりを継承▽日本の外交▽その他の国際ニュース",
        "content": "韓国のユン・ソンニョル政権は前政権が進めていた「脱原発」政策を撤回し、原発数を４基増やすほか発電割合も「３０％以上」に引き上げる方針を発表した。「小型モジュール炉」と呼ばれる原子炉の輸出拡大も進めることに。一方で、人材の確保と育成や放射性廃棄物の処理といった課題が指摘されている。韓国で始まった原発回帰とその課題に迫る。",
        "act": "【キャスター】油井秀樹，【キャスター】角谷直也，【キャスター】中川栞",
        "genres": [
          "0005",
          "0002",
          "0006"
        ]
      },
      {
        "id": "2022072918432",
        "event_id": "18432",
        "start_time": "2022-07-30T00:25:00+09:00",
        "end_time": "2022-07-30T02:10:00+09:00",
        "area": {
          "id": "130",
          "name": "東京"
        },
        "service": {
          "id": "g1",
          "name": "ＮＨＫ総合１",
          "logo_s": {
            "url": "//www.nhk.or.jp/common/img/media/gtv-100x50.png",
            "width": "100",
            "height": "50"
          },
          "logo_m": {
            "url": "//www.nhk.or.jp/common/img/media/gtv-200x100.png",
            "width": "200",
            "height": "100"
          },
          "logo_l": {
            "url": "//www.nhk.or.jp/common/img/media/gtv-200x200.png",
            "width": "200",
            "height": "200"
          }
        },
        "title": "ミッドナイトチャンネル",
        "subtitle": "",
        "content": "",
        "act": "",
        "genres": []
      },
      {
        "id": "2022072923052",
        "event_id": "23052",
        "start_time": "2022-07-30T02:10:00+09:00",
        "end_time": "2022-07-30T02:25:00+09:00",
        "area": {
          "id": "130",
          "name": "東京"
        },
        "service": {
          "id": "g1",
          "name": "ＮＨＫ総合１",
          "logo_s": {
            "url": "//www.nhk.or.jp/common/img/media/gtv-100x50.png",
            "width": "100",
            "height": "50"
          },
          "logo_m": {
            "url": "//www.nhk.or.jp/common/img/media/gtv-200x100.png",
            "width": "200",
            "height": "100"
          },
          "logo_l": {
            "url": "//www.nhk.or.jp/common/img/media/gtv-200x200.png",
            "width": "200",
            "height": "200"
          }
        },
        "title": "【連続テレビ小説】ちむどんどん（７１）「ウークイの夜」",
        "subtitle": "賢秀、良子、暢子、歌子が久しぶりにやんばるの実家に顔をそろえた。母・優子に起こった再婚話が気になったからだ。一方、和彦のもとに、沖縄での仕事が舞い込んでくる。",
        "content": "１９７８年８月。沖縄のお盆、ご先祖様をあの世へお見送りする最も重要な日「ウークイ」に、比嘉家の四きょうだい、賢秀（竜星涼）、良子（川口春奈）、暢子（黒島結菜）、歌子（上白石萌歌）が久しぶりにやんばるの実家に顔をそろえた。母・優子（仲間由紀恵）に起こった再婚話が気になったからだ。一方、新聞社の和彦（宮沢氷魚）のもとに、沖縄での大きな仕事のチャンスが舞い込んでくる。",
        "act": "【作】羽原大介，【出演】黒島結菜，仲間由紀恵，竜星涼，川口春奈，上白石萌歌，山中崇，山路和弘，原田美枝子，ジョン・カビラ，【音楽】岡部啓一，高田龍一，帆足圭吾",
        "genres": [
          "0300"
        ]
      },
      {
        "id": "2022072923053",
        "event_id": "23053",
        "start_time": "2022-07-30T02:25:00+09:00",
        "end_time": "2022-07-30T02:40:00+09:00",
        "area": {
          "id": "130",
          "name": "東京"
        },
        "service": {
          "id": "g1",
          "name": "ＮＨＫ総合１",
          "logo_s": {
            "url": "//www.nhk.or.jp/common/img/media/gtv-100x50.png",
            "width": "100",
            "height": "50"
          },
          "logo_m": {
            "url": "//www.nhk.or.jp/common/img/media/gtv-200x100.png",
            "width": "200",
            "height": "100"
          },
          "logo_l": {
            "url": "//www.nhk.or.jp/common/img/media/gtv-200x200.png",
            "width": "200",
            "height": "200"
          }
        },
        "title": "【連続テレビ小説】ちむどんどん（７２）「ウークイの夜」",
        "subtitle": "やんばるに帰省した暢子と賢秀。良子と歌子と四人そろったきょうだいは、優子に向かって、自分たちに何か隠していることがあるのかと問いただす。",
        "content": "お盆の頃、ひさしぶりにやんばるに帰省した暢子（黒島結菜）と賢秀（竜星涼）。良子（川口春奈）と歌子（上白石萌歌）と四人そろったきょうだいは、優子（仲間由紀恵）に向かって、自分たちに何か隠していることがあるのかと問いただす。その頃、和彦（宮沢氷魚）は取材で沖縄に入り、嘉手刈（津嘉山正種）という老人の取材に挑戦していた。だが、気難しそうな嘉手刈は、和彦に何も語ろうとはせず…。",
        "act": "【作】羽原大介，【出演】黒島結菜，仲間由紀恵，竜星涼，川口春奈，上白石萌歌，山中崇，原田美枝子，片岡鶴太郎，高嶋政伸，【音楽】岡部啓一，高田龍一，帆足圭吾",
        "genres": [
          "0300"
        ]
      },
      {
        "id": "2022072923054",
        "event_id": "23054",
        "start_time": "2022-07-30T02:40:00+09:00",
        "end_time": "2022-07-30T02:55:00+09:00",
        "area": {
          "id": "130",
          "name": "東京"
        },
        "service": {
          "id": "g1",
          "name": "ＮＨＫ総合１",
          "logo_s": {
            "url": "//www.nhk.or.jp/common/img/media/gtv-100x50.png",
            "width": "100",
            "height": "50"
          },
          "logo_m": {
            "url": "//www.nhk.or.jp/common/img/media/gtv-200x100.png",
            "width": "200",
            "height": "100"
          },
          "logo_l": {
            "url": "//www.nhk.or.jp/common/img/media/gtv-200x200.png",
            "width": "200",
            "height": "200"
          }
        },
        "title": "【連続テレビ小説】ちむどんどん（７３）「ウークイの夜」",
        "subtitle": "優子は、久しぶりにそろった四きょうだいに、自身の過去を話しはじめる。これまで四人には秘められていた亡き父と優子のなれそめなどだ。",
        "content": "優子（仲間由紀恵）は、久しぶりにそろった賢秀（竜星涼）、良子（川口春奈）、暢子（黒島結菜）、歌子（上白石萌歌）の四きょうだいに、自身の過去を話しはじめる。これまで四人には秘められていた亡き父と優子のなれそめなどだ。同じころ、東京のフォンターナでは房子（原田美枝子）が二ツ橋（高嶋政伸）に、鶴見では三郎（片岡鶴太郎）が田良島（山中崇）に、それぞれにずっと秘めてきた過去の思いを語る。",
        "act": "【作】羽原大介，【出演】黒島結菜，仲間由紀恵，竜星涼，川口春奈，上白石萌歌，山中崇，原田美枝子，片岡鶴太郎，高嶋政伸，【音楽】岡部啓一，高田龍一，帆足圭吾",
        "genres": [
          "0300"
        ]
      },
      {
        "id": "2022072923055",
        "event_id": "23055",
        "start_time": "2022-07-30T02:55:00+09:00",
        "end_time": "2022-07-30T03:10:00+09:00",
        "area": {
          "id": "130",
          "name": "東京"
        },
        "service": {
          "id": "g1",
          "name": "ＮＨＫ総合１",
          "logo_s": {
            "url": "//www.nhk.or.jp/common/img/media/gtv-100x50.png",
            "width": "100",
            "height": "50"
          },
          "logo_m": {
            "url": "//www.nhk.or.jp/common/img/media/gtv-200x100.png",
            "width": "200",
            "height": "100"
          },
          "logo_l": {
            "url": "//www.nhk.or.jp/common/img/media/gtv-200x200.png",
            "width": "200",
            "height": "200"
          }
        },
        "title": "【連続テレビ小説】ちむどんどん（７４）「ウークイの夜」",
        "subtitle": "沖縄のお盆の最終日、「ウークイ」に、暢子と賢秀、良子、歌子の四人は、優子から初めて亡き父とのなれそめなど、過去のいきさつを聞かされた。",
        "content": "沖縄のお盆の最終日、「ウークイ」に、暢子（黒島結菜）と賢秀（竜星涼）、良子（川口春奈）、歌子（上白石萌歌）の四人は、優子（仲間由紀恵）から初めて亡き父とのなれそめなど、過去のいきさつを聞く。四人はそれぞれに、多くの苦労を経てきた母の思いを受け止める。",
        "act": "【作】羽原大介，【出演】黒島結菜，仲間由紀恵，竜星涼，川口春奈，上白石萌歌，山中崇，原田美枝子，片岡鶴太郎，高嶋政伸，【音楽】岡部啓一，高田龍一，帆足圭吾",
        "genres": [
          "0300"
        ]
      },
      {
        "id": "2022072923056",
        "event_id": "23056",
        "start_time": "2022-07-30T03:10:00+09:00",
        "end_time": "2022-07-30T03:26:00+09:00",
        "area": {
          "id": "130",
          "name": "東京"
        },
        "service": {
          "id": "g1",
          "name": "ＮＨＫ総合１",
          "logo_s": {
            "url": "//www.nhk.or.jp/common/img/media/gtv-100x50.png",
            "width": "100",
            "height": "50"
          },
          "logo_m": {
            "url": "//www.nhk.or.jp/common/img/media/gtv-200x100.png",
            "width": "200",
            "height": "100"
          },
          "logo_l": {
            "url": "//www.nhk.or.jp/common/img/media/gtv-200x200.png",
            "width": "200",
            "height": "200"
          }
        },
        "title": "【連続テレビ小説】ちむどんどん（７５）「ウークイの夜」",
        "subtitle": "暢子と賢秀、良子、歌子の四きょうだいは、優子から過去の話を聞いた。一夜があけ、四人はそれぞれに思いを新たにして人生の課題に向き合おうとする。",
        "content": "暢子（黒島結菜）と賢秀（竜星涼）、良子（川口春奈）、歌子（上白石萌歌）の四きょうだいは、ウークイの夜に母・優子（仲間由紀恵）から過去の話を聞いた。母の話を受けて一夜があけて、四人は思いを新たにしてそれぞれの人生の課題に向き合おうとする。そんなとき暢子の前に現れたのは…。",
        "act": "【作】羽原大介，【出演】黒島結菜，仲間由紀恵，竜星涼，川口春奈，上白石萌歌，原田美枝子，山路和弘，【音楽】岡部啓一，高田龍一，帆足圭吾",
        "genres": [
          "0300"
        ]
      },
      {
        "id": "2022072923062",
        "event_id": "23062",
        "start_time": "2022-07-30T03:26:00+09:00",
        "end_time": "2022-07-30T03:41:00+09:00",
        "area": {
          "id": "130",
          "name": "東京"
        },
        "service": {
          "id": "g1",
          "name": "ＮＨＫ総合１",
          "logo_s": {
            "url": "//www.nhk.or.jp/common/img/media/gtv-100x50.png",
            "width": "100",
            "height": "50"
          },
          "logo_m": {
            "url": "//www.nhk.or.jp/common/img/media/gtv-200x100.png",
            "width": "200",
            "height": "100"
          },
          "logo_l": {
            "url": "//www.nhk.or.jp/common/img/media/gtv-200x200.png",
            "width": "200",
            "height": "200"
          }
        },
        "title": "【連続テレビ小説】ちむどんどん「第１５週　ウークイの夜」",
        "subtitle": "「ちむどんどん」第１５週を振り返る土曜版。沖縄に帰った暢子（黒島結菜）は兄妹とともに、優子（仲間由紀恵）から戦争の頃の話を聞くことに。一方、和彦（宮沢氷魚）も…",
        "content": "「ちむどんどん」第１５週を振り返る土曜版。沖縄に帰った暢子（黒島結菜）は賢秀（竜星涼）・良子（川口春奈）・歌子（上白石萌歌）とともに、優子（仲間由紀恵）の再婚話の真相を探るべく、共同売店に善一（山路和弘）を訪ねる。しかし優子は「ある用事」で不在だった。やがて帰宅した優子は子どもたちに、今まで伏せていた戦争の体験を語り始める。一方、和彦（宮沢氷魚）もとある取材のため、沖縄に入っていた…",
        "act": "【出演】黒島結菜，仲間由紀恵，竜星涼，川口春奈，上白石萌歌，宮沢氷魚，津嘉山正種，山路和弘，原田美枝子，【語り】ジョン・カビラ，【作】羽原大介",
        "genres": [
          "0300"
        ]
      },
      {
        "id": "2022072923063",
        "event_id": "23063",
        "start_time": "2022-07-30T03:41:00+09:00",
        "end_time": "2022-07-30T04:00:00+09:00",
        "area": {
          "id": "130",
          "name": "東京"
        },
        "service": {
          "id": "g1",
          "name": "ＮＨＫ総合１",
          "logo_s": {
            "url": "//www.nhk.or.jp/common/img/media/gtv-100x50.png",
            "width": "100",
            "height": "50"
          },
          "logo_m": {
            "url": "//www.nhk.or.jp/common/img/media/gtv-200x100.png",
            "width": "200",
            "height": "100"
          },
          "logo_l": {
            "url": "//www.nhk.or.jp/common/img/media/gtv-200x200.png",
            "width": "200",
            "height": "200"
          }
        },
        "title": "風景映像「沖縄　西表島」",
        "subtitle": "～沖縄県・西表島～",
        "content": "",
        "act": "",
        "genres": [
          "0802",
          "0801"
        ]
      },
      {
        "id": "2022072919021",
        "event_id": "19021",
        "start_time": "2022-07-30T04:00:00+09:00",
        "end_time": "2022-07-30T04:05:00+09:00",
        "area": {
          "id": "130",
          "name": "東京"
        },
        "service": {
          "id": "g1",
          "name": "ＮＨＫ総合１",
          "logo_s": {
            "url": "//www.nhk.or.jp/common/img/media/gtv-100x50.png",
            "width": "100",
            "height": "50"
          },
          "logo_m": {
            "url": "//www.nhk.or.jp/common/img/media/gtv-200x100.png",
            "width": "200",
            "height": "100"
          },
          "logo_l": {
            "url": "//www.nhk.or.jp/common/img/media/gtv-200x200.png",
            "width": "200",
            "height": "200"
          }
        },
        "title": "Ｄｏｋｉ　Ｄｏｋｉ！　ＮＨＫワールド　ＪＡＰＡＮ「ＳＤＧｓ関連番組の紹介」",
        "subtitle": "ＮＨＫワールドＪＡＰＡＮが展開するＳＤＧｓの取り組みを取り上げる。番組の魅力を伝えるとともに、「ＳＤＧｓ特設サイト」についてもアクセス方法などを併せて紹介する。",
        "content": "ＮＨＫワールドＪＡＰＡＮが展開するＳＤＧｓの取り組みを取り上げる。持続可能な日本のライフスタイルを描く「Ｓａｔｏｙａｍａ　Ｋｉｔｃｈｅｎ　Ｄｉａｒｙ」や「Ｚｅｒｏ　Ｗａｓｔｅ　Ｌｉｆｅ」などの番組の魅力を伝えるとともに、国際機関からも高く評価されたという、ＮＨＫワールドＪＡＰＡＮの「ＳＤＧｓ特設サイト」についても、アクセス方法や掲載情報などを併せて紹介する。",
        "act": "【司会】ゆりやんレトリィバァ，【声】岩井勇気",
        "genres": [
          "0207"
        ]
      },
      {
        "id": "2022072919022",
        "event_id": "19022",
        "start_time": "2022-07-30T04:05:00+09:00",
        "end_time": "2022-07-30T04:10:00+09:00",
        "area": {
          "id": "130",
          "name": "東京"
        },
        "service": {
          "id": "g1",
          "name": "ＮＨＫ総合１",
          "logo_s": {
            "url": "//www.nhk.or.jp/common/img/media/gtv-100x50.png",
            "width": "100",
            "height": "50"
          },
          "logo_m": {
            "url": "//www.nhk.or.jp/common/img/media/gtv-200x100.png",
            "width": "200",
            "height": "100"
          },
          "logo_l": {
            "url": "//www.nhk.or.jp/common/img/media/gtv-200x200.png",
            "width": "200",
            "height": "200"
          }
        },
        "title": "みんなのうた「想い出のグリーングラス」／「苺の花嫁さん」",
        "subtitle": "「想い出のグリーングラス」うた：上條恒彦、東京放送児童合唱団／「苺の花嫁さん」うた：麻呂とクニ河内",
        "content": "「想い出のグリーングラス」うた：上條恒彦、東京放送児童合唱団／「苺の花嫁さん」うた：麻呂とクニ河内",
        "act": "",
        "genres": [
          "0409",
          "0504"
        ]
      },
      {
        "id": "2022072919023",
        "event_id": "19023",
        "start_time": "2022-07-30T04:10:00+09:00",
        "end_time": "2022-07-30T04:20:00+09:00",
        "area": {
          "id": "130",
          "name": "東京"
        },
        "service": {
          "id": "g1",
          "name": "ＮＨＫ総合１",
          "logo_s": {
            "url": "//www.nhk.or.jp/common/img/media/gtv-100x50.png",
            "width": "100",
            "height": "50"
          },
          "logo_m": {
            "url": "//www.nhk.or.jp/common/img/media/gtv-200x100.png",
            "width": "200",
            "height": "100"
          },
          "logo_l": {
            "url": "//www.nhk.or.jp/common/img/media/gtv-200x200.png",
            "width": "200",
            "height": "200"
          }
        },
        "title": "時論公論　【出演】ＮＨＫ解説委員",
        "subtitle": "▽混沌（とん）とした時代、次々と押し寄せるニュースの裏に、何があるのか？“明日を生きる指針”を提供する解説番組。",
        "content": "",
        "act": "",
        "genres": [
          "0006",
          "0000",
          "0007"
        ]
      }
    ]
  }
}
