{
  "list": {
    "s3": [
      {
        "id": "2022081327507",
        "event_id": "27507",
        "start_time": "2022-08-13T05:00:00+09:00",
        "end_time": "2022-08-13T05:10:00+09:00",
        "area": {
          "id": "130",
          "name": "東京"
        },
        "service": {
          "id": "s3",
          "name": "ＮＨＫＢＳプレミアム",
          "logo_s": {
            "url": "//www.nhk.or.jp/common/img/media/bsp-100x50.png",
            "width": "100",
            "height": "50"
          },
          "logo_m": {
            "url": "//www.nhk.or.jp/common/img/media/bsp-200x100.png",
            "width": "200",
            "height": "100"
          },
          "logo_l": {
            "url": "//www.nhk.or.jp/common/img/media/bsp-200x200.png",
            "width": "200",
            "height": "200"
          }
        },
        "title": "ハイビジョン動物記「キビタイヒスイインコ」",
        "subtitle": "",
        "content": "",
        "act": "",
        "genres": [
          "0802"
        ]
      },
      {
        "id": "2022081327508",
        "event_id": "27508",
        "start_time": "2022-08-13T05:10:00+09:00",
        "end_time": "2022-08-13T05:27:00+09:00",
        "area": {
          "id": "130",
          "name": "東京"
        },
        "service": {
          "id": "s3",
          "name": "ＮＨＫＢＳプレミアム",
          "logo_s": {
            "url": "//www.nhk.or.jp/common/img/media/bsp-100x50.png",
            "width": "100",
            "height": "50"
          },
          "logo_m": {
            "url": "//www.nhk.or.jp/common/img/media/bsp-200x100.png",
            "width": "200",
            "height": "100"
          },
          "logo_l": {
            "url": "//www.nhk.or.jp/common/img/media/bsp-200x200.png",
            "width": "200",
            "height": "200"
          }
        },
        "title": "自然へのいざない　流氷に生きるタテゴトアザラシ～カナダ・ニューファンドランド島",
        "subtitle": "「流氷に生きるタテゴトアザラシ　～カナダ・ニューファンドランド島」",
        "content": "",
        "act": "",
        "genres": [
          "0802"
        ]
      },
      {
        "id": "2022081327510",
        "event_id": "27510",
        "start_time": "2022-08-13T05:27:00+09:00",
        "end_time": "2022-08-13T06:05:00+09:00",
        "area": {
          "id": "130",
          "name": "東京"
        },
        "service": {
          "id": "s3",
          "name": "ＮＨＫＢＳプレミアム",
          "logo_s": {
            "url": "//www.nhk.or.jp/common/img/media/bsp-100x50.png",
            "width": "100",
            "height": "50"
          },
          "logo_m": {
            "url": "//www.nhk.or.jp/common/img/media/bsp-200x100.png",
            "width": "200",
            "height": "100"
          },
          "logo_l": {
            "url": "//www.nhk.or.jp/common/img/media/bsp-200x200.png",
            "width": "200",
            "height": "200"
          }
        },
        "title": "よみがえる新日本紀行　選「盆・花火の里～福島県・浅川町～」",
        "subtitle": "昭和５４年、福島県浅川町を訪ねた新日本紀行をふたたび。お盆に行われる花火大会。地元青年会が二手に分かれて手作り花火を競い合う熱気あふれる街の夏が描かれている。",
        "content": "新日本紀行から４２年、花火の里・浅川町を再訪した。３００年以上守り継がれてきた花火は今も町の暮らしに息づいている。家の軒下に吊るされた花火の殻は古くからの魔よけ。この風習をもとに町の名物を発案した人は子どもの頃からの大の花火好き。冠婚葬祭に合わせた“花火の出張打ち上げ”も健在だ。お盆の花火大会は昨年はコロナ禍のため中止に。町の人たちは今年こそ伝統の夜空の彩りを楽しみたいと大会開催を待ちわびる。",
        "act": "【語り】森田美由紀",
        "genres": [
          "0801"
        ]
      },
      {
        "id": "2022081327511",
        "event_id": "27511",
        "start_time": "2022-08-13T06:05:00+09:00",
        "end_time": "2022-08-13T06:30:00+09:00",
        "area": {
          "id": "130",
          "name": "東京"
        },
        "service": {
          "id": "s3",
          "name": "ＮＨＫＢＳプレミアム",
          "logo_s": {
            "url": "//www.nhk.or.jp/common/img/media/bsp-100x50.png",
            "width": "100",
            "height": "50"
          },
          "logo_m": {
            "url": "//www.nhk.or.jp/common/img/media/bsp-200x100.png",
            "width": "200",
            "height": "100"
          },
          "logo_l": {
            "url": "//www.nhk.or.jp/common/img/media/bsp-200x200.png",
            "width": "200",
            "height": "200"
          }
        },
        "title": "小さな旅　選「この山に逢（あ）いたくて～北アルプス　朝日岳～」",
        "subtitle": "花の山として知られる北アルプス・朝日岳。亡き父から受け継いだ山小屋を守る女性管理人。５０年以上朝日岳に通う男性。つながりを大切に山とともに生きる人々を訪ねます。",
        "content": "富山、長野、新潟からいくつものルートで登ることができる北アルプス朝日岳。長い登山道に多種多様な高山植物が咲く花の山として知られています。山頂の近くにある山小屋の女性管理人は、亡き父から受け継いだ「安全を守る心」を大切に登山者を迎えています。朝日岳を仕事場にしていた時に山の魅力を知り、５０年通い続ける人。朝日岳に魅せられた山岳写真家。人と人とのつながりを大切に、山とともに生きる人たちを訪ねます。",
        "act": "【旅人】山本哲也",
        "genres": [
          "0801",
          "0800",
          "0804"
        ]
      },
      {
        "id": "2022081327512",
        "event_id": "27512",
        "start_time": "2022-08-13T06:30:00+09:00",
        "end_time": "2022-08-13T06:45:00+09:00",
        "area": {
          "id": "130",
          "name": "東京"
        },
        "service": {
          "id": "s3",
          "name": "ＮＨＫＢＳプレミアム",
          "logo_s": {
            "url": "//www.nhk.or.jp/common/img/media/bsp-100x50.png",
            "width": "100",
            "height": "50"
          },
          "logo_m": {
            "url": "//www.nhk.or.jp/common/img/media/bsp-200x100.png",
            "width": "200",
            "height": "100"
          },
          "logo_l": {
            "url": "//www.nhk.or.jp/common/img/media/bsp-200x200.png",
            "width": "200",
            "height": "200"
          }
        },
        "title": "さわやか自然百景「栃木　高原山」",
        "subtitle": "栃木県北部の高原山はいくつもの峰が連なる火山。山肌から湧き出す豊かな水と火山ならではの地形が多くの生きものを支えている。春から初夏、躍動する命のドラマを追う。",
        "content": "栃木県北部の高原山。標高１７００メートル級の峰々が連なる山の総称で、今も噴気をあげる火山である。春、山腹を覆う森の一角、火山活動でできたくぼ地に雪解け水がたまり、湿地が現われる。そこに冬眠から目覚めた数千匹ものクロサンショウウオが集まり大産卵！懸命に命を繋ぐ。初夏、トンボが次々に羽化し、湿地を飛び交う。夜、水辺の木の枝ではモリアオガエルが必死に産卵場所を目指す。春から初夏、高原山で命の躍動を追う。",
        "act": "【語り】豊島実季",
        "genres": [
          "0802",
          "1000"
        ]
      },
      {
        "id": "2022081327515",
        "event_id": "27515",
        "start_time": "2022-08-13T06:45:00+09:00",
        "end_time": "2022-08-13T07:15:00+09:00",
        "area": {
          "id": "130",
          "name": "東京"
        },
        "service": {
          "id": "s3",
          "name": "ＮＨＫＢＳプレミアム",
          "logo_s": {
            "url": "//www.nhk.or.jp/common/img/media/bsp-100x50.png",
            "width": "100",
            "height": "50"
          },
          "logo_m": {
            "url": "//www.nhk.or.jp/common/img/media/bsp-200x100.png",
            "width": "200",
            "height": "100"
          },
          "logo_l": {
            "url": "//www.nhk.or.jp/common/img/media/bsp-200x200.png",
            "width": "200",
            "height": "200"
          }
        },
        "title": "美の壺「桃山の革命　織部焼」",
        "subtitle": "桃山時代が生んだユニークな「織部焼」。深みのある緑に、型破りなデザイン、抽象的な文様。いかにして生まれ、何を意味するのか…陶芸界の革命・織部焼の魅力に迫る！",
        "content": "織部焼に見惚れた料理人・奥田透さんによる、織部と料理の組み合わせの技！▽古美術商イチオシの、ゆがんだ「沓（くつ）茶碗」とは！？▽美濃の織部焼が、なぜ京都で大量に発見されたのか？▽２００もの織部の型を写し取った陶芸家が追及する、織部の技法とは？▽耳の長いウサギに、かごの目…織部に描かれた文様は、いったい何を意味しているのか？▽革新の精神を受け継ぐ、現代織部のド迫力！＜Ｆｉｌｅ５６３＞",
        "act": "【出演】草刈正雄，日本料理店店主…奥田透，古美術商…梶高明，陶芸家…小山智徳，学習院大学教授…荒川正明，陶芸家…玉置保夫，【語り】木村多江",
        "genres": [
          "1002",
          "0804",
          "0202"
        ]
      },
      {
        "id": "2022081327518",
        "event_id": "27518",
        "start_time": "2022-08-13T07:15:00+09:00",
        "end_time": "2022-08-13T07:30:00+09:00",
        "area": {
          "id": "130",
          "name": "東京"
        },
        "service": {
          "id": "s3",
          "name": "ＮＨＫＢＳプレミアム",
          "logo_s": {
            "url": "//www.nhk.or.jp/common/img/media/bsp-100x50.png",
            "width": "100",
            "height": "50"
          },
          "logo_m": {
            "url": "//www.nhk.or.jp/common/img/media/bsp-200x100.png",
            "width": "200",
            "height": "100"
          },
          "logo_l": {
            "url": "//www.nhk.or.jp/common/img/media/bsp-200x200.png",
            "width": "200",
            "height": "200"
          }
        },
        "title": "【連続テレビ小説】芋たこなんきん（１２１）「子離れ、親離れ」",
        "subtitle": "大阪の商店勤め、３７歳独身の楽天娘が、ある日恋に落ち、結婚へ。しかし、なんと嫁ぎ先は１０人の大家族だった！２００６年放送の連続テレビ小説。笑いと涙のホームドラマ",
        "content": "眼鏡がイヤで学校を休んだ亜紀（鍋本帆乃香）を見舞いに、亜紀が恋心を寄せる同級生が訪ねてくる。また、高層団地に一人で住むことにした母・和代（香川京子）が町子（藤山直美）を訪ねる。和代の一人暮らしを心配する町子に、和代はこれからの楽しみを話す。和代が期待する自身の未来に納得した町子であったが、信夫（西興一朗）は、新婚で移り住む予定だったマンションを解約し、これまでどおり和代のそばにいるという。",
        "act": "【原案】田辺聖子，【出演】藤山直美，國村隼，イーデス・ハンソン，邑野みあ，西興一朗，鍋本帆乃香，香川京子，いしだあゆみ，【語り】住田功一，【脚本】長川千佳子，【音楽】栗山和樹",
        "genres": [
          "0300"
        ]
      },
      {
        "id": "2022081327519",
        "event_id": "27519",
        "start_time": "2022-08-13T07:30:00+09:00",
        "end_time": "2022-08-13T08:00:00+09:00",
        "area": {
          "id": "130",
          "name": "東京"
        },
        "service": {
          "id": "s3",
          "name": "ＮＨＫＢＳプレミアム",
          "logo_s": {
            "url": "//www.nhk.or.jp/common/img/media/bsp-100x50.png",
            "width": "100",
            "height": "50"
          },
          "logo_m": {
            "url": "//www.nhk.or.jp/common/img/media/bsp-200x100.png",
            "width": "200",
            "height": "100"
          },
          "logo_l": {
            "url": "//www.nhk.or.jp/common/img/media/bsp-200x200.png",
            "width": "200",
            "height": "200"
          }
        },
        "title": "ニッポンぶらり鉄道旅「なまらけっぱるを探して　ＪＲ函館本線　長万部～小樽」",
        "subtitle": "ＪＲ函館本線で、長万部から小樽へ。素敵な木工の工房に、湖の不思議な美しさ、甘くて驚きのじゃがいもに、ご当地リキュールまで！北海道の魅力を伝える人々に出会う旅！",
        "content": "なまらけっぱる（とてもがんばる）人たちを探して長万部から小樽へ。【昆布】木工職人たちが開いたユニーク工房【比羅夫】半月湖で自然の織りなす不思議な模様を撮るカメラマン【倶知安】驚くほど甘いじゃがいもの焼き芋！秘密は特別に寝かせた芋にあり！【余市】生産農家ごとに風味が違うご当地リキュール！繊細な味を堪能！【小樽】地元産ホタテを使った町おこし。イベントからＰＲソングまで！驚きの味わいと地元の人の心意気！",
        "act": "【語り】ＴＡＲＡＫＯ，【リポーター】宮崎香蓮",
        "genres": [
          "1000",
          "0505",
          "0801"
        ]
      },
      {
        "id": "2022081327522",
        "event_id": "27522",
        "start_time": "2022-08-13T08:00:00+09:00",
        "end_time": "2022-08-13T09:00:00+09:00",
        "area": {
          "id": "130",
          "name": "東京"
        },
        "service": {
          "id": "s3",
          "name": "ＮＨＫＢＳプレミアム",
          "logo_s": {
            "url": "//www.nhk.or.jp/common/img/media/bsp-100x50.png",
            "width": "100",
            "height": "50"
          },
          "logo_m": {
            "url": "//www.nhk.or.jp/common/img/media/bsp-200x100.png",
            "width": "200",
            "height": "100"
          },
          "logo_l": {
            "url": "//www.nhk.or.jp/common/img/media/bsp-200x200.png",
            "width": "200",
            "height": "200"
          }
        },
        "title": "いいＺｏｏだね。～岩合光昭の動物園歩き～「和歌山」",
        "subtitle": "動物写真家・岩合光昭が和歌山県の「アドベンチャーワールド」を訪れ、パンダのかわいさの奥にある「野性」に迫る。ペンギン、モモイロペリカン、ヒマラヤタールも登場。",
        "content": "岩合光昭ｖｓ．パンダ一家。「四角いパンダ」って何？▽水中を「飛ぶ」ペンギン。▽モモイロペリカンの便利なクチバシ。▽巨大なシロサイ同士が大激突。▽マントヒヒの群れを観察して見えてくるものとは？▽ナレーターは白石涼子。",
        "act": "【出演】岩合光昭，【語り】白石涼子",
        "genres": [
          "1001"
        ]
      },
      {
        "id": "2022081327524",
        "event_id": "27524",
        "start_time": "2022-08-13T09:00:00+09:00",
        "end_time": "2022-08-13T09:30:00+09:00",
        "area": {
          "id": "130",
          "name": "東京"
        },
        "service": {
          "id": "s3",
          "name": "ＮＨＫＢＳプレミアム",
          "logo_s": {
            "url": "//www.nhk.or.jp/common/img/media/bsp-100x50.png",
            "width": "100",
            "height": "50"
          },
          "logo_m": {
            "url": "//www.nhk.or.jp/common/img/media/bsp-200x100.png",
            "width": "200",
            "height": "100"
          },
          "logo_l": {
            "url": "//www.nhk.or.jp/common/img/media/bsp-200x200.png",
            "width": "200",
            "height": "200"
          }
        },
        "title": "医師が教える！極上健康旅「熱海」",
        "subtitle": "医師がプロデュースする新たな旅番組。舞台は熱海。グルメや絶景を楽しみながら歩き方や温泉の入り方のコツで腰痛やひざ痛を改善！徳川家康の長寿の秘密も熱海にあり！？",
        "content": "全国を旅しながら絶景を楽しみ、おいしいものを味わい、さらに「健康」になれたら最高だと思いませんか？そんなわがままな旅を医療の専門家にプロデュースしてもらう新たな旅番組。今回の旅の舞台は熱海。全国有数の温泉地である熱海は長寿で有名な徳川家康も愛した地。歩き方や温泉の入り方などのちょっとしたコツで腰痛やひざ痛を解消する方法を紹介！モデルコースからスケジュール、食事まで。医師が教える極上健康旅に出発",
        "act": "【出演】みほとけ，鈴木拓，遼河はるひ",
        "genres": [
          "1000"
        ]
      },
      {
        "id": "2022081329125",
        "event_id": "29125",
        "start_time": "2022-08-13T09:30:00+09:00",
        "end_time": "2022-08-13T09:45:00+09:00",
        "area": {
          "id": "130",
          "name": "東京"
        },
        "service": {
          "id": "s3",
          "name": "ＮＨＫＢＳプレミアム",
          "logo_s": {
            "url": "//www.nhk.or.jp/common/img/media/bsp-100x50.png",
            "width": "100",
            "height": "50"
          },
          "logo_m": {
            "url": "//www.nhk.or.jp/common/img/media/bsp-200x100.png",
            "width": "200",
            "height": "100"
          },
          "logo_l": {
            "url": "//www.nhk.or.jp/common/img/media/bsp-200x200.png",
            "width": "200",
            "height": "200"
          }
        },
        "title": "岩合光昭の世界ネコ歩きｍｉｎｉ「濡れるのはイヤ」「ネコのごろん」",
        "subtitle": "岩合光昭が撮るネコ。冒頭は「濡れるのはイヤ」。「猫識」は「ネコのごろん」。名場面はオーストラリア・シドニーと山形県鶴岡市から。",
        "content": "動物写真家・岩合光昭が撮る世界のネコの映像。５９分版からの再構成。▽冒頭は濡れるのを嫌がるネコたち。▽「猫識」は「ネコのごろん」。お腹を見せるお馴染みの仕草にはいろいろな意味が…。▽名場面はシドニー・マンリービーチと山形県鶴岡市の「花の寺」から。▽語り：悠木碧",
        "act": "【出演】岩合光昭，【語り】悠木碧",
        "genres": [
          "1001"
        ]
      },
      {
        "id": "2022081327526",
        "event_id": "27526",
        "start_time": "2022-08-13T09:45:00+09:00",
        "end_time": "2022-08-13T10:00:00+09:00",
        "area": {
          "id": "130",
          "name": "東京"
        },
        "service": {
          "id": "s3",
          "name": "ＮＨＫＢＳプレミアム",
          "logo_s": {
            "url": "//www.nhk.or.jp/common/img/media/bsp-100x50.png",
            "width": "100",
            "height": "50"
          },
          "logo_m": {
            "url": "//www.nhk.or.jp/common/img/media/bsp-200x100.png",
            "width": "200",
            "height": "100"
          },
          "logo_l": {
            "url": "//www.nhk.or.jp/common/img/media/bsp-200x200.png",
            "width": "200",
            "height": "200"
          }
        },
        "title": "【連続テレビ小説】ちむどんどん（８６）「しあわせのアンダンスー」",
        "subtitle": "三郎のお陰で、フォンターナの問題は解決した。そして暢子は、自分たちの披露宴はフォンターナで行うと決意。しかし、結婚への大きな課題はそのままで…。",
        "content": "暢子（黒島結菜）が勤めるフォンターナに、三郎（片岡鶴太郎）のお陰で、平和が戻ってきた。ただ、房子（原田美枝子）と三郎の再会は果たせなかった。暢子は、大事な人を集めた披露宴をフォンターナで行おうと決意する。しかし、重子（鈴木保奈美）からはまだ和彦（宮沢氷魚）との結婚を認めてもらっていない。そんな中、良子（川口春奈）が、妹の結婚のために動き出すことに。",
        "act": "【作】羽原大介，【出演】黒島結菜，仲間由紀恵，川口春奈，鈴木保奈美，原田美枝子，【音楽】岡部啓一，高田龍一，帆足圭吾",
        "genres": [
          "0300"
        ]
      },
      {
        "id": "2022081327527",
        "event_id": "27527",
        "start_time": "2022-08-13T10:00:00+09:00",
        "end_time": "2022-08-13T10:15:00+09:00",
        "area": {
          "id": "130",
          "name": "東京"
        },
        "service": {
          "id": "s3",
          "name": "ＮＨＫＢＳプレミアム",
          "logo_s": {
            "url": "//www.nhk.or.jp/common/img/media/bsp-100x50.png",
            "width": "100",
            "height": "50"
          },
          "logo_m": {
            "url": "//www.nhk.or.jp/common/img/media/bsp-200x100.png",
            "width": "200",
            "height": "100"
          },
          "logo_l": {
            "url": "//www.nhk.or.jp/common/img/media/bsp-200x200.png",
            "width": "200",
            "height": "200"
          }
        },
        "title": "【連続テレビ小説】ちむどんどん（８７）「しあわせのアンダンスー」",
        "subtitle": "暢子が重子に「おいしいものを作りたい」と意気込んでいると、房子は暢子に意外な提案する。その頃、和彦の実家を良子が訪ねていた。",
        "content": "暢子（黒島結菜）は和彦（宮沢氷魚）と重子（鈴木保奈美）を再びフォンターナに招待するつもりだ。暢子が「おいしいものを出したい」と意気込んでいると、オーナーの房子（原田美枝子）は暢子に意外な提案する。その頃、良子（川口春奈）は、なんと和彦の実家を訪ねていた。暢子と和彦の結婚に賛成してくれるように、重子を説得するためだった。ところがそこにさらにもうひとりの人物が現れる…。",
        "act": "【作】羽原大介，【出演】黒島結菜，仲間由紀恵，竜星涼，川口春奈，上白石萌歌，鈴木保奈美，高嶋政伸，原田美枝子，【音楽】岡部啓一，高田龍一，帆足圭吾",
        "genres": [
          "0300"
        ]
      },
      {
        "id": "2022081327528",
        "event_id": "27528",
        "start_time": "2022-08-13T10:15:00+09:00",
        "end_time": "2022-08-13T10:30:00+09:00",
        "area": {
          "id": "130",
          "name": "東京"
        },
        "service": {
          "id": "s3",
          "name": "ＮＨＫＢＳプレミアム",
          "logo_s": {
            "url": "//www.nhk.or.jp/common/img/media/bsp-100x50.png",
            "width": "100",
            "height": "50"
          },
          "logo_m": {
            "url": "//www.nhk.or.jp/common/img/media/bsp-200x100.png",
            "width": "200",
            "height": "100"
          },
          "logo_l": {
            "url": "//www.nhk.or.jp/common/img/media/bsp-200x200.png",
            "width": "200",
            "height": "200"
          }
        },
        "title": "【連続テレビ小説】ちむどんどん（８８）「しあわせのアンダンスー」",
        "subtitle": "暢子は重子を再びフォンターナに招待する。暢子が重子に出したのは、房子のアドバイスのおかげで作れた、とある「おいしくない」料理の数々だった。果たして重子は…。",
        "content": "重子（鈴木保奈美）を訪ねた良子（川口春奈）と賢秀（竜星涼）。暢子（黒島結菜）と和彦（宮沢氷魚）の結婚に賛成するように説得をするつもりが、話しは思うように進まず終わってしまった。暢子は重子を再びフォンターナに招待する。暢子が重子に出したのは、房子（原田美枝子）のアドバイスのおかげで作れた、とある重子にとって懐かしい料理の数々だった。果たして重子は…。",
        "act": "【作】羽原大介，【出演】黒島結菜，仲間由紀恵，上白石萌歌，鈴木保奈美，原田美枝子，【音楽】岡部啓一，高田龍一，帆足圭吾",
        "genres": [
          "0300"
        ]
      },
      {
        "id": "2022081327529",
        "event_id": "27529",
        "start_time": "2022-08-13T10:30:00+09:00",
        "end_time": "2022-08-13T10:45:00+09:00",
        "area": {
          "id": "130",
          "name": "東京"
        },
        "service": {
          "id": "s3",
          "name": "ＮＨＫＢＳプレミアム",
          "logo_s": {
            "url": "//www.nhk.or.jp/common/img/media/bsp-100x50.png",
            "width": "100",
            "height": "50"
          },
          "logo_m": {
            "url": "//www.nhk.or.jp/common/img/media/bsp-200x100.png",
            "width": "200",
            "height": "100"
          },
          "logo_l": {
            "url": "//www.nhk.or.jp/common/img/media/bsp-200x200.png",
            "width": "200",
            "height": "200"
          }
        },
        "title": "【連続テレビ小説】ちむどんどん（８９）「しあわせのアンダンスー」",
        "subtitle": "フォンターナで暢子と和彦の披露宴が行われる。房子などフォンターナのスタッフ、優子ほかやんばるの面々、そして鶴見の三郎たちがいよいよ一同に会することに。",
        "content": "暢子（黒島結菜）は、フォンターナで重子（鈴木保奈美）になつかしい料理を振舞い、やっと和彦（宮沢氷魚）との結婚に賛成してもらうことができた。それから半年後、フォンターナで暢子と和彦の披露宴が行われることになる。重子に加え、房子（原田美枝子）などフォンターナのスタッフ、優子（仲間由紀恵）ほかやんばるの面々、そして鶴見の三郎（片岡鶴太郎）たちがいよいよ一同に会することに…。",
        "act": "【作】羽原大介，【出演】黒島結菜，仲間由紀恵，竜星涼，川口春奈，上白石萌歌，山中崇，鈴木保奈美，高嶋政伸，片岡鶴太郎，原田美枝子，【語り】ジョン・カビラ，【音楽】岡部啓一，高田龍一，帆足圭吾",
        "genres": [
          "0300"
        ]
      },
      {
        "id": "2022081327530",
        "event_id": "27530",
        "start_time": "2022-08-13T10:45:00+09:00",
        "end_time": "2022-08-13T11:00:00+09:00",
        "area": {
          "id": "130",
          "name": "東京"
        },
        "service": {
          "id": "s3",
          "name": "ＮＨＫＢＳプレミアム",
          "logo_s": {
            "url": "//www.nhk.or.jp/common/img/media/bsp-100x50.png",
            "width": "100",
            "height": "50"
          },
          "logo_m": {
            "url": "//www.nhk.or.jp/common/img/media/bsp-200x100.png",
            "width": "200",
            "height": "100"
          },
          "logo_l": {
            "url": "//www.nhk.or.jp/common/img/media/bsp-200x200.png",
            "width": "200",
            "height": "200"
          }
        },
        "title": "【連続テレビ小説】ちむどんどん（９０）「しあわせのアンダンスー」",
        "subtitle": "迎えた結婚式当日。フォンターナでは、暢子の思いが溢れる数々の料理が宴を彩る。そして暢子は披露宴で、とある思いをひらめいてしまい…。",
        "content": "暢子（黒島結菜）と和彦（宮沢氷魚）の結婚式披露宴の日がやってきた。披露宴が行われているフォンターナでは、暢子の思いが溢れる数々の料理が宴を彩る。千葉の養豚場では賢秀（竜星涼）が思わぬ事態に陥って披露宴への出席が危うくなっていた。そして暢子は披露宴で、とある思いをひらめいてしまい…。",
        "act": "【作】羽原大介，【出演】黒島結菜，仲間由紀恵，上白石萌歌，山中崇，鈴木保奈美，中原丈雄，高嶋政伸，片岡鶴太郎，原田美枝子，【語り】ジョン・カビラ，【音楽】岡部啓一，高田龍一，帆足圭吾",
        "genres": [
          "0300"
        ]
      },
      {
        "id": "2022081327531",
        "event_id": "27531",
        "start_time": "2022-08-13T11:00:00+09:00",
        "end_time": "2022-08-13T12:00:00+09:00",
        "area": {
          "id": "130",
          "name": "東京"
        },
        "service": {
          "id": "s3",
          "name": "ＮＨＫＢＳプレミアム",
          "logo_s": {
            "url": "//www.nhk.or.jp/common/img/media/bsp-100x50.png",
            "width": "100",
            "height": "50"
          },
          "logo_m": {
            "url": "//www.nhk.or.jp/common/img/media/bsp-200x100.png",
            "width": "200",
            "height": "100"
          },
          "logo_l": {
            "url": "//www.nhk.or.jp/common/img/media/bsp-200x200.png",
            "width": "200",
            "height": "200"
          }
        },
        "title": "プレミアムセレクション",
        "subtitle": "",
        "content": "",
        "act": "",
        "genres": []
      },
      {
        "id": "2022081327532",
        "event_id": "27532",
        "start_time": "2022-08-13T12:00:00+09:00",
        "end_time": "2022-08-13T13:30:00+09:00",
        "area": {
          "id": "130",
          "name": "東京"
        },
        "service": {
          "id": "s3",
          "name": "ＮＨＫＢＳプレミアム",
          "logo_s": {
            "url": "//www.nhk.or.jp/common/img/media/bsp-100x50.png",
            "width": "100",
            "height": "50"
          },
          "logo_m": {
            "url": "//www.nhk.or.jp/common/img/media/bsp-200x100.png",
            "width": "200",
            "height": "100"
          },
          "logo_l": {
            "url": "//www.nhk.or.jp/common/img/media/bsp-200x200.png",
            "width": "200",
            "height": "200"
          }
        },
        "title": "新・ＢＳ日本のうた　夏スペシャル「第一夜・天童、三山、丘のワンマンショー」",
        "subtitle": "豪華３人のＳＰワンマンショー！デビュー５０年の天童が代表曲の数々を披露！三山が持ち歌をたっぷりと、英語の名曲にも挑戦！丘は女の情念を演じて魅せる！ＳＰゲストも！",
        "content": "【三山ひろしワンマンショー】「人恋酒場」「ダンチョネ港町」「この胸のときめきを」「北の大地」「白雲の城」「人生援歌」「夢追い人」「お岩木山」【丘みどりワンマンショー】「北の螢」「お祭りマンボ」「花月夜」「白山雪舞い」「雪陽炎」「佐渡の夕笛」【天童よしみワンマンショー】「あんたの花道」「夜明け」「涙の破片」「あなたに咲いた花だから」「あれから」「道頓堀人情」「珍島物語」ほか",
        "act": "【出演】丘みどり，天童よしみ，三山ひろし，おおい大輔，工藤あやの，津吹みゆ，羽山みずき，花柳糸之，松前ひろ子，【司会】渡辺健太，【出演】中尾唱，ＢＳ日本のうた楽団",
        "genres": [
          "0404"
        ]
      },
      {
        "id": "2022081333801",
        "event_id": "33801",
        "start_time": "2022-08-13T13:30:00+09:00",
        "end_time": "2022-08-13T15:00:00+09:00",
        "area": {
          "id": "130",
          "name": "東京"
        },
        "service": {
          "id": "s3",
          "name": "ＮＨＫＢＳプレミアム",
          "logo_s": {
            "url": "//www.nhk.or.jp/common/img/media/bsp-100x50.png",
            "width": "100",
            "height": "50"
          },
          "logo_m": {
            "url": "//www.nhk.or.jp/common/img/media/bsp-200x100.png",
            "width": "200",
            "height": "100"
          },
          "logo_l": {
            "url": "//www.nhk.or.jp/common/img/media/bsp-200x200.png",
            "width": "200",
            "height": "200"
          }
        },
        "title": "歴史発掘ミステリー　京都　千年蔵「幕末奇譚　知を武器にかく闘えり」",
        "subtitle": "京都の蔵に眠る文化財を全部出し調査。知られざる歴史を発掘する千年蔵。舞台は江戸時代のオタクの学び舎。西郷も岩倉をも惹きつけた脅威の知の力を最新科学で再現！！",
        "content": "京都の蔵に眠る文化財を全部出し調査。知られざる歴史を発掘する京都千年蔵。第２回の舞台は江戸時代の「オタクの楽園」と言われた学び舎。７５１２点の文化財を徹底調査。膨大な量の生物標本。カラクリ蔵の天井に記された謎のメッセージ。オタク学者の銃や刀ではなく「知」を武器にした戦いに最新科学が挑む。西郷＆岩倉！！維新の英雄たちを惹きつけたオタク結社とは？発掘！！江戸時代版Ｗｉｋｉｐｅｄｉａ＆元祖！！万国博覧会",
        "act": "【司会】磯田道史，【出演】高橋源一郎，ヤマザキマリ，笹野高史，【語り】窪田等，【アナウンサー】渡邊佐和子",
        "genres": [
          "0801"
        ]
      },
      {
        "id": "2022081327536",
        "event_id": "27536",
        "start_time": "2022-08-13T15:00:00+09:00",
        "end_time": "2022-08-13T16:00:00+09:00",
        "area": {
          "id": "130",
          "name": "東京"
        },
        "service": {
          "id": "s3",
          "name": "ＮＨＫＢＳプレミアム",
          "logo_s": {
            "url": "//www.nhk.or.jp/common/img/media/bsp-100x50.png",
            "width": "100",
            "height": "50"
          },
          "logo_m": {
            "url": "//www.nhk.or.jp/common/img/media/bsp-200x100.png",
            "width": "200",
            "height": "100"
          },
          "logo_l": {
            "url": "//www.nhk.or.jp/common/img/media/bsp-200x200.png",
            "width": "200",
            "height": "200"
          }
        },
        "title": "世界大惨事大全「スペースシャトル　コロンビア号　空中分解事故」",
        "subtitle": "大惨事に至る道のりを丹念にたどり、「驚き、発見する」スペシャル番組。今回は、乗組員７名全員が命を落としたスペースシャトル・コロンビア号空中分解事故の悲劇に迫る。",
        "content": "人類の歴史は失敗の歴史である。そんな歴史上の“大いなる失敗”にフォーカスし、破局への道のりを丹念にたどり、「驚き、発見する」スペシャル番組。大惨事はなぜ起きたのか？失敗の教訓は生かされたのか？　今回は、乗組員７名全員が命を落としたスペースシャトル、コロンビア号の空中分解事故に迫る。事故調査報告書が指摘したのは、直接の事故原因以上にエリート集団・ＮＡＳＡという組織が抱えるより根深く深刻な問題だった…",
        "act": "【出演】山崎直子，松尾亜紀子，入山章栄，辻田真佐憲，【語り】石川由依",
        "genres": [
          "0801",
          "0803",
          "0800"
        ]
      },
      {
        "id": "2022081328355",
        "event_id": "28355",
        "start_time": "2022-08-13T16:00:00+09:00",
        "end_time": "2022-08-13T16:16:00+09:00",
        "area": {
          "id": "130",
          "name": "東京"
        },
        "service": {
          "id": "s3",
          "name": "ＮＨＫＢＳプレミアム",
          "logo_s": {
            "url": "//www.nhk.or.jp/common/img/media/bsp-100x50.png",
            "width": "100",
            "height": "50"
          },
          "logo_m": {
            "url": "//www.nhk.or.jp/common/img/media/bsp-200x100.png",
            "width": "200",
            "height": "100"
          },
          "logo_l": {
            "url": "//www.nhk.or.jp/common/img/media/bsp-200x200.png",
            "width": "200",
            "height": "200"
          }
        },
        "title": "世界ふれあい街歩き　ちょっとお散歩▽新たな一歩　踏みだす街　シアトル～アメリカ",
        "subtitle": "アメリカ西海岸の都市、シアトルは、世界的なベンチャー企業を生み出してきた。新たな人生を求め、各地から訪れる人々たちと出会う。（初回放送：２０１７年１０月２４日）",
        "content": "アメリカ西海岸、世界的なベンチャー企業が生まれたことで有名なシアトル。自然豊かな環境は、さまざまな人たちをひきつける。威勢のよい声で投げながら大きな魚を売る市場。１１７０度の高熱で加工するガラス工房には、全米各地から若者が訪れる。イランから難民としてやってきたという親子は、公園でダンスを楽しみながら、新たな人生を切り開こうとしている。人々をひきつける街に暮らす人たちと出会う。",
        "act": "【語り】鹿島綾乃",
        "genres": [
          "0801"
        ]
      },
      {
        "id": "2022081328451",
        "event_id": "28451",
        "start_time": "2022-08-13T16:16:00+09:00",
        "end_time": "2022-08-13T16:26:00+09:00",
        "area": {
          "id": "130",
          "name": "東京"
        },
        "service": {
          "id": "s3",
          "name": "ＮＨＫＢＳプレミアム",
          "logo_s": {
            "url": "//www.nhk.or.jp/common/img/media/bsp-100x50.png",
            "width": "100",
            "height": "50"
          },
          "logo_m": {
            "url": "//www.nhk.or.jp/common/img/media/bsp-200x100.png",
            "width": "200",
            "height": "100"
          },
          "logo_l": {
            "url": "//www.nhk.or.jp/common/img/media/bsp-200x200.png",
            "width": "200",
            "height": "200"
          }
        },
        "title": "にっぽん百名山ミニ　１０ｍｉｎ「初夏　西日本の山々」",
        "subtitle": "石垣島の於茂登岳（５２６ｍ）美ら海を育む沖縄最高峰！屋久島の永田岳（１８８６ｍ）世界遺産の屋久杉の森を越え白き頂へ！大台ヶ原山（１６９５ｍ）清流の峡谷を遡る！",
        "content": "【石垣島・於茂登岳】亜熱帯のジャングルに流れる清流を遡り、湧き出す水を浴びながら、沖縄県最高峰をめざす！琉球竹に覆われた山頂からは美ら海のサンゴ礁も！【屋久島・永田岳】屋久杉の巨木の森を巡り、白い花崗岩の巨大な塔がそびえ立つ峰々の大展望を満喫し、九州第２位の高峰めざす！【大台ケ原山】日本有数の峡谷・大杉谷を遡り、清らかな水の山を旅する！天空から降り注ぐ千尋の滝や、岩と水の宮殿・シシ淵は幽玄の世界！",
        "act": "【出演】八幡暁，田中俊三，内炭孝夫，【語り】鈴木麻里子",
        "genres": [
          "0802"
        ]
      },
      {
        "id": "2022081327538",
        "event_id": "27538",
        "start_time": "2022-08-13T16:26:00+09:00",
        "end_time": "2022-08-13T18:00:00+09:00",
        "area": {
          "id": "130",
          "name": "東京"
        },
        "service": {
          "id": "s3",
          "name": "ＮＨＫＢＳプレミアム",
          "logo_s": {
            "url": "//www.nhk.or.jp/common/img/media/bsp-100x50.png",
            "width": "100",
            "height": "50"
          },
          "logo_m": {
            "url": "//www.nhk.or.jp/common/img/media/bsp-200x100.png",
            "width": "200",
            "height": "100"
          },
          "logo_l": {
            "url": "//www.nhk.or.jp/common/img/media/bsp-200x200.png",
            "width": "200",
            "height": "200"
          }
        },
        "title": "刑事コロンボ（４７）「狂ったシナリオ」",
        "subtitle": "何度見ても新しい！ミステリードラマの金字塔。若き特撮映画監督が旧友を殺害し、遺体の身元がわからないよう工作…パトリック・ウィリアムズの音楽がエミー賞にノミネート",
        "content": "映画監督アレックス・ブレイディのもとを、旧友のレニーが１本のフィルムを持って訪ねてくる。そこにはブレイディの秘密が映し出されており、それを公表するというのだ。キャリアを守りたいブレイディは、レニーをオープンセットへと連れ出し感電死させる。その後、身元をわからないようにして海岸に遺体を遺棄した。だが、遺体のそばに落ちていた１冊の本から、ブレイディのシナリオは狂い始める。",
        "act": "ピーター・フォーク…石田太郎，フィッシャー・スティーブンス…池田秀一，モリー・ヘイガン…佐々木優子，ナン・マーティン…此島愛子，スティーブン・ヒル…池田勝，【演出】ジェームズ・フローリー，【脚本】リチャード・アラン・シモンズ",
        "genres": [
          "0301"
        ]
      },
      {
        "id": "2022081327539",
        "event_id": "27539",
        "start_time": "2022-08-13T18:00:00+09:00",
        "end_time": "2022-08-13T19:30:00+09:00",
        "area": {
          "id": "130",
          "name": "東京"
        },
        "service": {
          "id": "s3",
          "name": "ＮＨＫＢＳプレミアム",
          "logo_s": {
            "url": "//www.nhk.or.jp/common/img/media/bsp-100x50.png",
            "width": "100",
            "height": "50"
          },
          "logo_m": {
            "url": "//www.nhk.or.jp/common/img/media/bsp-200x100.png",
            "width": "200",
            "height": "100"
          },
          "logo_l": {
            "url": "//www.nhk.or.jp/common/img/media/bsp-200x200.png",
            "width": "200",
            "height": "200"
          }
        },
        "title": "ゆったり温泉ひとり旅",
        "subtitle": "",
        "content": "",
        "act": "",
        "genres": [
          "0801"
        ]
      },
      {
        "id": "2022081327541",
        "event_id": "27541",
        "start_time": "2022-08-13T19:30:00+09:00",
        "end_time": "2022-08-13T21:00:00+09:00",
        "area": {
          "id": "130",
          "name": "東京"
        },
        "service": {
          "id": "s3",
          "name": "ＮＨＫＢＳプレミアム",
          "logo_s": {
            "url": "//www.nhk.or.jp/common/img/media/bsp-100x50.png",
            "width": "100",
            "height": "50"
          },
          "logo_m": {
            "url": "//www.nhk.or.jp/common/img/media/bsp-200x100.png",
            "width": "200",
            "height": "100"
          },
          "logo_l": {
            "url": "//www.nhk.or.jp/common/img/media/bsp-200x200.png",
            "width": "200",
            "height": "200"
          }
        },
        "title": "ＮＩＧＨＴ　ＺＯＯ～夜のパンダ大中継～",
        "subtitle": "夜の動物園からドキドキの大中継！愛らしいパンダは何してる？暗闇のサファリでライオンを探索！動物の赤ちゃんも次々登場する和歌山・アドベンチャーワールドから生放送。",
        "content": "和歌山・アドベンチャーワールドから夜の動物たちを生中継！なんといっても注目なのがパンダ。一昨年生まれた楓浜をはじめ７頭ものパンダが夜食をほおばったり、うつらうつら眠ったりと、愛らしい姿を見せてくれる。さらにナイトサファリでは突然現れるキリンやサイ、肉をくらうライオンなどのドキドキシーンが満載！さらにパンダやペンギン、チーターなどの赤ちゃん飼育ドキュメントもご紹介。家族で楽しめる夏休みの特別番組。",
        "act": "【出演】遠藤憲一，ウエンツ瑛士，長濱ねる",
        "genres": [
          "0802"
        ]
      },
      {
        "id": "2022081329156",
        "event_id": "29156",
        "start_time": "2022-08-13T21:00:00+09:00",
        "end_time": "2022-08-13T22:00:00+09:00",
        "area": {
          "id": "130",
          "name": "東京"
        },
        "service": {
          "id": "s3",
          "name": "ＮＨＫＢＳプレミアム",
          "logo_s": {
            "url": "//www.nhk.or.jp/common/img/media/bsp-100x50.png",
            "width": "100",
            "height": "50"
          },
          "logo_m": {
            "url": "//www.nhk.or.jp/common/img/media/bsp-200x100.png",
            "width": "200",
            "height": "100"
          },
          "logo_l": {
            "url": "//www.nhk.or.jp/common/img/media/bsp-200x200.png",
            "width": "200",
            "height": "200"
          }
        },
        "title": "玉置浩二　シンフォニックコンサート　ｉｎ　河口湖",
        "subtitle": "４０周年を迎えた玉置浩二の集大成となるオーケストラとのコンサート▽安全地帯・ソロの名曲をたっぷりと▽劇場との知られざる物語▽玉置の音楽への深い思いに迫る",
        "content": "今年デビュー４０周年を迎えた玉置浩二の集大成となるオーケストラとのコンサート▽「ワインレッドの心」「田園」そして「夏の終りのハーモニー」など安全地帯・ソロの名曲の数々をオーケストラとの珠玉の共演で送る▽２２年ぶりにコンサートを行った河口湖ステラシアターとの知られざるストーリーにも迫る▽「命つきるまで歌いたい」玉置浩二の音楽への深い思いに迫る",
        "act": "【出演】玉置浩二，群馬交響楽団，大友直人",
        "genres": [
          "0400"
        ]
      },
      {
        "id": "2022081327544",
        "event_id": "27544",
        "start_time": "2022-08-13T22:00:00+09:00",
        "end_time": "2022-08-13T23:30:00+09:00",
        "area": {
          "id": "130",
          "name": "東京"
        },
        "service": {
          "id": "s3",
          "name": "ＮＨＫＢＳプレミアム",
          "logo_s": {
            "url": "//www.nhk.or.jp/common/img/media/bsp-100x50.png",
            "width": "100",
            "height": "50"
          },
          "logo_m": {
            "url": "//www.nhk.or.jp/common/img/media/bsp-200x100.png",
            "width": "200",
            "height": "100"
          },
          "logo_l": {
            "url": "//www.nhk.or.jp/common/img/media/bsp-200x200.png",
            "width": "200",
            "height": "200"
          }
        },
        "title": "世界サブカルチャー史　欲望の系譜「フランス　興亡の６０ｓ」",
        "subtitle": "６０年代フランス特別編。闘争の季節に起きた２つの革命が社会にもたらしたのは？伝統と革新がせめぎ合う、花の都パリのリアルを探せ！異色歴史ドキュメント。語り玉木宏。",
        "content": "ゴダール、トリュフォー、シルヴィ・バルタンからカトリーヌ・ドヌーヴ、ジャン＝ポール・ベルモンドまでポップとシリアスが、政治と芸術が交差した６０年代のパリで若者達が求めていた社会は？「勝手にしやがれ」「ピアニストを撃て」「地下鉄のザジ」「女は女である」「突然炎のごとく」「気狂いピエロ」「中国女」「夜霧の恋人たち」…アメリカともソ連とも異なる独自の道を模索した国の大衆のエネルギー。想像力の旅の行方は？",
        "act": "【出演】カイエ・デュ・シネマ元編集長…ジャン＝ミシェル・フロドン，歴史学者…パスカル・オリー，【語り】玉木宏，【声】古賀慶太，品田美穂",
        "genres": [
          "0804"
        ]
      },
      {
        "id": "2022081327546",
        "event_id": "27546",
        "start_time": "2022-08-13T23:30:00+09:00",
        "end_time": "2022-08-14T01:01:00+09:00",
        "area": {
          "id": "130",
          "name": "東京"
        },
        "service": {
          "id": "s3",
          "name": "ＮＨＫＢＳプレミアム",
          "logo_s": {
            "url": "//www.nhk.or.jp/common/img/media/bsp-100x50.png",
            "width": "100",
            "height": "50"
          },
          "logo_m": {
            "url": "//www.nhk.or.jp/common/img/media/bsp-200x100.png",
            "width": "200",
            "height": "100"
          },
          "logo_l": {
            "url": "//www.nhk.or.jp/common/img/media/bsp-200x200.png",
            "width": "200",
            "height": "200"
          }
        },
        "title": "フランスで新発見！幕末ニッポンの秘宝「将軍からの贈り物」",
        "subtitle": "幕末、日本がフランス皇帝に贈った豪華な美術品が発見された。欧米列強の脅威が迫る中、生き残りをかけて送った贈答品に秘められた幕末ニッポンの物語をひもとく。",
        "content": "徳川将軍から皇帝ナポレオン３世に贈られた大量の美術品。びょうぶ、掛け軸、漆器など、日本の芸術の粋を集めた豪華な美術品の数々。そこには圧倒的な軍事力で開国を余儀なくされた日本の、世界に向けた驚きのメッセージが秘められていた。今回、幕末、外国に贈られたお宝を求め世界各地を取材。開国から幕府崩壊まで１３年間。欧米にたびたび派遣された使節団のドラマチックな物語とともに幕末の贈答品外交秘話をひもとく。",
        "act": "【リポーター】雨宮塔子，【語り】眞島秀和，早見沙織",
        "genres": [
          "0801",
          "1002",
          "0804"
        ]
      },
      {
        "id": "2022081328579",
        "event_id": "28579",
        "start_time": "2022-08-14T01:01:00+09:00",
        "end_time": "2022-08-14T03:45:00+09:00",
        "area": {
          "id": "130",
          "name": "東京"
        },
        "service": {
          "id": "s3",
          "name": "ＮＨＫＢＳプレミアム",
          "logo_s": {
            "url": "//www.nhk.or.jp/common/img/media/bsp-100x50.png",
            "width": "100",
            "height": "50"
          },
          "logo_m": {
            "url": "//www.nhk.or.jp/common/img/media/bsp-200x100.png",
            "width": "200",
            "height": "100"
          },
          "logo_l": {
            "url": "//www.nhk.or.jp/common/img/media/bsp-200x200.png",
            "width": "200",
            "height": "200"
          }
        },
        "title": "宝塚歌劇　月組公演「桜嵐記」「Ｄｒｅａｍ　Ｃｈａｓｅｒ」",
        "subtitle": "宝塚大劇場での月組トップコンビ、珠城りょうと美園さくらの退団公演「桜嵐記（おうらんき）」と「Ｄｒｅａｍ　Ｃｈａｓｅｒ」を劇場の臨場感そのままにお送りする。",
        "content": "宝塚大劇場で上演された月組トップコンビ、珠城りょうと美園さくらの退団公演をお送りする。第１部は南北朝の動乱を舞台に描かれる日本物のミュージカル、ロマン・トラジック「桜嵐記（おうらんき）」。第２部はトップスター・珠城りょうの夢を詰め込んだ、きらびやかでゴージャスなステージ、スーパー・ファンタジー「Ｄｒｅａｍ　Ｃｈａｓｅｒ」。劇場の臨場感そのままに公演の魅力をお届けする。",
        "act": "【出演】珠城りょう，美園さくら，宝塚歌劇団月組，【アナウンサー】青柳万美",
        "genres": [
          "0915"
        ]
      },
      {
        "id": "2022081328584",
        "event_id": "28584",
        "start_time": "2022-08-14T03:45:00+09:00",
        "end_time": "2022-08-14T03:50:00+09:00",
        "area": {
          "id": "130",
          "name": "東京"
        },
        "service": {
          "id": "s3",
          "name": "ＮＨＫＢＳプレミアム",
          "logo_s": {
            "url": "//www.nhk.or.jp/common/img/media/bsp-100x50.png",
            "width": "100",
            "height": "50"
          },
          "logo_m": {
            "url": "//www.nhk.or.jp/common/img/media/bsp-200x100.png",
            "width": "200",
            "height": "100"
          },
          "logo_l": {
            "url": "//www.nhk.or.jp/common/img/media/bsp-200x200.png",
            "width": "200",
            "height": "200"
          }
        },
        "title": "にっぽん百名山ミニ　３ｍｉｎ「春　宮之浦岳」",
        "subtitle": "屋久島の宮之浦岳（１９３６ｍ）、世界自然遺産の屋久杉の森を巡る山旅！“もののけ姫”のモデルとされる苔むす森、幹回り１６ｍ以上の縄文杉、山頂の大展望など見所満載！",
        "content": "洋上のアルプス・屋久島の宮之浦岳をめざす山旅！４月、白谷雲水峡を出発！６６０種以上のコケが生える島の中でも人気の苔むす森へ！幻想的な潤い豊かな自然からジブリアニメが着想された。屋久杉の森で樹齢２０００年以上の縄文杉と出会う。栄養の乏しい土壌で時間をかけて成長したため、こうした巨木が生まれたのだ。巨岩が転がる開けた尾根を登り、太平洋の大海原が望める山頂へ、！案内するのは、登山ガイドの神崎真貴雄さん。",
        "act": "【出演】神崎真貴雄，【語り】鈴木麻里子",
        "genres": [
          "0802"
        ]
      },
      {
        "id": "2022081328586",
        "event_id": "28586",
        "start_time": "2022-08-14T03:50:00+09:00",
        "end_time": "2022-08-14T04:00:00+09:00",
        "area": {
          "id": "130",
          "name": "東京"
        },
        "service": {
          "id": "s3",
          "name": "ＮＨＫＢＳプレミアム",
          "logo_s": {
            "url": "//www.nhk.or.jp/common/img/media/bsp-100x50.png",
            "width": "100",
            "height": "50"
          },
          "logo_m": {
            "url": "//www.nhk.or.jp/common/img/media/bsp-200x100.png",
            "width": "200",
            "height": "100"
          },
          "logo_l": {
            "url": "//www.nhk.or.jp/common/img/media/bsp-200x200.png",
            "width": "200",
            "height": "200"
          }
        },
        "title": "にっぽんごはん紀行「かゆずし」",
        "subtitle": "－山形・酒田市－【ナレーション】山根基世",
        "content": "",
        "act": "【ナレーション】山根基世",
        "genres": [
          "0801",
          "0205"
        ]
      },
      {
        "id": "2022081328587",
        "event_id": "28587",
        "start_time": "2022-08-14T04:00:00+09:00",
        "end_time": "2022-08-14T05:00:00+09:00",
        "area": {
          "id": "130",
          "name": "東京"
        },
        "service": {
          "id": "s3",
          "name": "ＮＨＫＢＳプレミアム",
          "logo_s": {
            "url": "//www.nhk.or.jp/common/img/media/bsp-100x50.png",
            "width": "100",
            "height": "50"
          },
          "logo_m": {
            "url": "//www.nhk.or.jp/common/img/media/bsp-200x100.png",
            "width": "200",
            "height": "100"
          },
          "logo_l": {
            "url": "//www.nhk.or.jp/common/img/media/bsp-200x200.png",
            "width": "200",
            "height": "200"
          }
        },
        "title": "ＭＵＳＴ　ＢＥ　ＵＫＴＶ　▽ロッド・スチュワート，クリフ・リチャード　ほか",
        "subtitle": "ノンストップの洋楽プログラム。７０年代にイギリスで放送された音楽番組「ＳＵＰＥＲＳＯＮＩＣ」から１７組のアーティストのパフォーマンス映像をお届けする。",
        "content": "今回パフォーマンスを繰り広げるのは、ロッド・スチュワート、クリフ・リチャード、ジャスティン・ヘイワード、デヴィッド・エセックス、リヴァプール・エクスプレス、アンディ・フェアウェザー・ロウ、アンディ・ボウン、ブルー、キャサリン・ハウ、ザ・ニュー・シーカーズ、Ｒ＆Ｊ・ストーン、マーク・ボラン＆グロリア・ジョーンズ、マリアンヌ・フェイスフルほか全１７組。（古い映像のため一部に乱れがあります）",
        "act": "",
        "genres": [
          "0401"
        ]
      }
    ]
  }
}
